[{"name": "", "pa": 185, "era": 6.73, "xera": -2.148, "era_diff": 8.88, "woba": 0.389, "xwoba": 0.0, "woba_diff": 0.389, "barrel_pct": 0.0, "hard_hit": 0.0, "exit_velo": 0.0, "whiff_pct": 0.0}, {"name": "", "pa": 251, "era": 4.24, "xera": -2.059, "era_diff": 6.3, "woba": 0.319, "xwoba": 0.0, "woba_diff": 0.319, "barrel_pct": 0.0, "hard_hit": 0.0, "exit_velo": 0.0, "whiff_pct": 0.0}, {"name": "", "pa": 191, "era": 4.33, "xera": -1.887, "era_diff": 6.22, "woba": 0.322, "xwoba": 0.0, "woba_diff": 0.322, "barrel_pct": 0.0, "hard_hit": 0.0, "exit_velo": 0.0, "whiff_pct": 0.0}, {"name": "", "pa": 160, "era": 5.37, "xera": -1.834, "era_diff": 7.2, "woba": 0.354, "xwoba": 0.0, "woba_diff": 0.354, "barrel_pct": 0.0, "hard_hit": 0.0, "exit_velo": 0.0, "whiff_pct": 0.0}, {"name": "", "pa": 433, "era": 5.06, "xera": -1.646, "era_diff": 6.71, "woba": 0.345, "xwoba": 0.0, "woba_diff": 0.345, "barrel_pct": 0.0, "hard_hit": 0.0, "exit_velo": 0.0, "whiff_pct": 0.0}, {"name": "", "pa": 169, "era": 4.96, "xera": -1.644, "era_diff": 6.6, "woba": 0.342, "xwoba": 0.0, "woba_diff": 0.342, "barrel_pct": 0.0, "hard_hit": 0.0, "exit_velo": 0.0, "whiff_pct": 0.0}, {"name": "", "pa": 289, "era": 3.41, "xera": -1.605, "era_diff": 5.02, "woba": 0.288, "xwoba": 0.0, "woba_diff": 0.288, "barrel_pct": 0.0, "hard_hit": 0.0, "exit_velo": 0.0, "whiff_pct": 0.0}, {"name": "", "pa": 174, "era": 8.26, "xera": -1.605, "era_diff": 9.87, "woba": 0.422, "xwoba": 0.0, "woba_diff": 0.422, "barrel_pct": 0.0, "hard_hit": 0.0, "exit_velo": 0.0, "whiff_pct": 0.0}, {"name": "", "pa": 280, "era": 4.04, "xera": -1.545, "era_diff": 5.58, "woba": 0.312, "xwoba": 0.0, "woba_diff": 0.312, "barrel_pct": 0.0, "hard_hit": 0.0, "exit_velo": 0.0, "whiff_pct": 0.0}, {"name": "", "pa": 433, "era": 5.37, "xera": -1.532, "era_diff": 6.9, "woba": 0.354, "xwoba": 0.0, "woba_diff": 0.354, "barrel_pct": 0.0, "hard_hit": 0.0, "exit_velo": 0.0, "whiff_pct": 0.0}, {"name": "", "pa": 212, "era": 4.55, "xera": -1.491, "era_diff": 6.04, "woba": 0.329, "xwoba": 0.0, "woba_diff": 0.329, "barrel_pct": 0.0, "hard_hit": 0.0, "exit_velo": 0.0, "whiff_pct": 0.0}, {"name": "", "pa": 168, "era": 3.48, "xera": -1.414, "era_diff": 4.89, "woba": 0.291, "xwoba": 0.0, "woba_diff": 0.291, "barrel_pct": 0.0, "hard_hit": 0.0, "exit_velo": 0.0, "whiff_pct": 0.0}, {"name": "", "pa": 139, "era": 3.56, "xera": -1.4, "era_diff": 4.96, "woba": 0.294, "xwoba": 0.0, "woba_diff": 0.294, "barrel_pct": 0.0, "hard_hit": 0.0, "exit_velo": 0.0, "whiff_pct": 0.0}, {"name": "", "pa": 254, "era": 4.45, "xera": -1.382, "era_diff": 5.83, "woba": 0.326, "xwoba": 0.0, "woba_diff": 0.326, "barrel_pct": 0.0, "hard_hit": 0.0, "exit_velo": 0.0, "whiff_pct": 0.0}, {"name": "", "pa": 190, "era": 3.51, "xera": -1.335, "era_diff": 4.84, "woba": 0.292, "xwoba": 0.0, "woba_diff": 0.292, "barrel_pct": 0.0, "hard_hit": 0.0, "exit_velo": 0.0, "whiff_pct": 0.0}, {"name": "", "pa": 126, "era": 3.48, "xera": -1.306, "era_diff": 4.79, "woba": 0.291, "xwoba": 0.0, "woba_diff": 0.291, "barrel_pct": 0.0, "hard_hit": 0.0, "exit_velo": 0.0, "whiff_pct": 0.0}, {"name": "", "pa": 235, "era": 4.13, "xera": -1.293, "era_diff": 5.42, "woba": 0.315, "xwoba": 0.0, "woba_diff": 0.315, "barrel_pct": 0.0, "hard_hit": 0.0, "exit_velo": 0.0, "whiff_pct": 0.0}, {"name": "", "pa": 338, "era": 3.02, "xera": -1.289, "era_diff": 4.31, "woba": 0.272, "xwoba": 0.0, "woba_diff": 0.272, "barrel_pct": 0.0, "hard_hit": 0.0, "exit_velo": 0.0, "whiff_pct": 0.0}, {"name": "", "pa": 175, "era": 4.67, "xera": -1.259, "era_diff": 5.93, "woba": 0.333, "xwoba": 0.0, "woba_diff": 0.333, "barrel_pct": 0.0, "hard_hit": 0.0, "exit_velo": 0.0, "whiff_pct": 0.0}, {"name": "", "pa": 445, "era": 4.3, "xera": -1.24, "era_diff": 5.54, "woba": 0.321, "xwoba": 0.0, "woba_diff": 0.321, "barrel_pct": 0.0, "hard_hit": 0.0, "exit_velo": 0.0, "whiff_pct": 0.0}, {"name": "", "pa": 412, "era": 5.2, "xera": -1.235, "era_diff": 6.44, "woba": 0.349, "xwoba": 0.0, "woba_diff": 0.349, "barrel_pct": 0.0, "hard_hit": 0.0, "exit_velo": 0.0, "whiff_pct": 0.0}, {"name": "", "pa": 189, "era": 3.69, "xera": -1.235, "era_diff": 4.92, "woba": 0.299, "xwoba": 0.0, "woba_diff": 0.299, "barrel_pct": 0.0, "hard_hit": 0.0, "exit_velo": 0.0, "whiff_pct": 0.0}, {"name": "", "pa": 215, "era": 3.96, "xera": -1.224, "era_diff": 5.18, "woba": 0.309, "xwoba": 0.0, "woba_diff": 0.309, "barrel_pct": 0.0, "hard_hit": 0.0, "exit_velo": 0.0, "whiff_pct": 0.0}, {"name": "", "pa": 173, "era": 3.88, "xera": -1.222, "era_diff": 5.1, "woba": 0.306, "xwoba": 0.0, "woba_diff": 0.306, "barrel_pct": 0.0, "hard_hit": 0.0, "exit_velo": 0.0, "whiff_pct": 0.0}, {"name": "", "pa": 339, "era": 3.88, "xera": -1.211, "era_diff": 5.09, "woba": 0.306, "xwoba": 0.0, "woba_diff": 0.306, "barrel_pct": 0.0, "hard_hit": 0.0, "exit_velo": 0.0, "whiff_pct": 0.0}, {"name": "", "pa": 171, "era": 3.64, "xera": -1.211, "era_diff": 4.85, "woba": 0.297, "xwoba": 0.0, "woba_diff": 0.297, "barrel_pct": 0.0, "hard_hit": 0.0, "exit_velo": 0.0, "whiff_pct": 0.0}, {"name": "", "pa": 179, "era": 3.85, "xera": -1.209, "era_diff": 5.06, "woba": 0.305, "xwoba": 0.0, "woba_diff": 0.305, "barrel_pct": 0.0, "hard_hit": 0.0, "exit_velo": 0.0, "whiff_pct": 0.0}, {"name": "", "pa": 160, "era": 3.82, "xera": -1.186, "era_diff": 5.01, "woba": 0.304, "xwoba": 0.0, "woba_diff": 0.304, "barrel_pct": 0.0, "hard_hit": 0.0, "exit_velo": 0.0, "whiff_pct": 0.0}, {"name": "", "pa": 184, "era": 4.13, "xera": -1.171, "era_diff": 5.3, "woba": 0.315, "xwoba": 0.0, "woba_diff": 0.315, "barrel_pct": 0.0, "hard_hit": 0.0, "exit_velo": 0.0, "whiff_pct": 0.0}, {"name": "", "pa": 140, "era": 4.19, "xera": -1.17, "era_diff": 5.36, "woba": 0.317, "xwoba": 0.0, "woba_diff": 0.317, "barrel_pct": 0.0, "hard_hit": 0.0, "exit_velo": 0.0, "whiff_pct": 0.0}, {"name": "", "pa": 525, "era": 5.81, "xera": -1.167, "era_diff": 6.98, "woba": 0.366, "xwoba": 0.0, "woba_diff": 0.366, "barrel_pct": 0.0, "hard_hit": 0.0, "exit_velo": 0.0, "whiff_pct": 0.0}, {"name": "", "pa": 263, "era": 3.88, "xera": -1.151, "era_diff": 5.03, "woba": 0.306, "xwoba": 0.0, "woba_diff": 0.306, "barrel_pct": 0.0, "hard_hit": 0.0, "exit_velo": 0.0, "whiff_pct": 0.0}, {"name": "", "pa": 142, "era": 3.09, "xera": -1.151, "era_diff": 4.24, "woba": 0.275, "xwoba": 0.0, "woba_diff": 0.275, "barrel_pct": 0.0, "hard_hit": 0.0, "exit_velo": 0.0, "whiff_pct": 0.0}, {"name": "", "pa": 156, "era": 3.43, "xera": -1.148, "era_diff": 4.58, "woba": 0.289, "xwoba": 0.0, "woba_diff": 0.289, "barrel_pct": 0.0, "hard_hit": 0.0, "exit_velo": 0.0, "whiff_pct": 0.0}, {"name": "", "pa": 157, "era": 3.74, "xera": -1.147, "era_diff": 4.89, "woba": 0.301, "xwoba": 0.0, "woba_diff": 0.301, "barrel_pct": 0.0, "hard_hit": 0.0, "exit_velo": 0.0, "whiff_pct": 0.0}, {"name": "", "pa": 504, "era": 4.48, "xera": -1.132, "era_diff": 5.61, "woba": 0.327, "xwoba": 0.0, "woba_diff": 0.327, "barrel_pct": 0.0, "hard_hit": 0.0, "exit_velo": 0.0, "whiff_pct": 0.0}, {"name": "", "pa": 204, "era": 4.13, "xera": -1.13, "era_diff": 5.26, "woba": 0.315, "xwoba": 0.0, "woba_diff": 0.315, "barrel_pct": 0.0, "hard_hit": 0.0, "exit_velo": 0.0, "whiff_pct": 0.0}, {"name": "", "pa": 146, "era": 5.09, "xera": -1.125, "era_diff": 6.21, "woba": 0.346, "xwoba": 0.0, "woba_diff": 0.346, "barrel_pct": 0.0, "hard_hit": 0.0, "exit_velo": 0.0, "whiff_pct": 0.0}, {"name": "", "pa": 478, "era": 3.99, "xera": -1.117, "era_diff": 5.11, "woba": 0.31, "xwoba": 0.0, "woba_diff": 0.31, "barrel_pct": 0.0, "hard_hit": 0.0, "exit_velo": 0.0, "whiff_pct": 0.0}, {"name": "", "pa": 149, "era": 3.99, "xera": -1.114, "era_diff": 5.1, "woba": 0.31, "xwoba": 0.0, "woba_diff": 0.31, "barrel_pct": 0.0, "hard_hit": 0.0, "exit_velo": 0.0, "whiff_pct": 0.0}, {"name": "", "pa": 192, "era": 4.19, "xera": -1.108, "era_diff": 5.3, "woba": 0.317, "xwoba": 0.0, "woba_diff": 0.317, "barrel_pct": 0.0, "hard_hit": 0.0, "exit_velo": 0.0, "whiff_pct": 0.0}, {"name": "", "pa": 175, "era": 2.76, "xera": -1.087, "era_diff": 3.85, "woba": 0.26, "xwoba": 0.0, "woba_diff": 0.26, "barrel_pct": 0.0, "hard_hit": 0.0, "exit_velo": 0.0, "whiff_pct": 0.0}, {"name": "", "pa": 138, "era": 2.82, "xera": -1.087, "era_diff": 3.91, "woba": 0.263, "xwoba": 0.0, "woba_diff": 0.263, "barrel_pct": 0.0, "hard_hit": 0.0, "exit_velo": 0.0, "whiff_pct": 0.0}, {"name": "", "pa": 169, "era": 4.36, "xera": -1.078, "era_diff": 5.44, "woba": 0.323, "xwoba": 0.0, "woba_diff": 0.323, "barrel_pct": 0.0, "hard_hit": 0.0, "exit_velo": 0.0, "whiff_pct": 0.0}, {"name": "", "pa": 396, "era": 4.07, "xera": -1.077, "era_diff": 5.15, "woba": 0.313, "xwoba": 0.0, "woba_diff": 0.313, "barrel_pct": 0.0, "hard_hit": 0.0, "exit_velo": 0.0, "whiff_pct": 0.0}, {"name": "", "pa": 197, "era": 4.04, "xera": -1.07, "era_diff": 5.11, "woba": 0.312, "xwoba": 0.0, "woba_diff": 0.312, "barrel_pct": 0.0, "hard_hit": 0.0, "exit_velo": 0.0, "whiff_pct": 0.0}, {"name": "", "pa": 159, "era": 4.48, "xera": -1.064, "era_diff": 5.54, "woba": 0.327, "xwoba": 0.0, "woba_diff": 0.327, "barrel_pct": 0.0, "hard_hit": 0.0, "exit_velo": 0.0, "whiff_pct": 0.0}, {"name": "", "pa": 425, "era": 5.2, "xera": -1.051, "era_diff": 6.25, "woba": 0.349, "xwoba": 0.0, "woba_diff": 0.349, "barrel_pct": 0.0, "hard_hit": 0.0, "exit_velo": 0.0, "whiff_pct": 0.0}, {"name": "", "pa": 197, "era": 4.02, "xera": -1.048, "era_diff": 5.07, "woba": 0.311, "xwoba": 0.0, "woba_diff": 0.311, "barrel_pct": 0.0, "hard_hit": 0.0, "exit_velo": 0.0, "whiff_pct": 0.0}, {"name": "", "pa": 442, "era": 5.13, "xera": -1.03, "era_diff": 6.16, "woba": 0.347, "xwoba": 0.0, "woba_diff": 0.347, "barrel_pct": 0.0, "hard_hit": 0.0, "exit_velo": 0.0, "whiff_pct": 0.0}, {"name": "", "pa": 168, "era": 6.08, "xera": -0.962, "era_diff": 7.04, "woba": 0.373, "xwoba": 0.0, "woba_diff": 0.373, "barrel_pct": 0.0, "hard_hit": 0.0, "exit_velo": 0.0, "whiff_pct": 0.0}, {"name": "", "pa": 165, "era": 3.12, "xera": -0.96, "era_diff": 4.08, "woba": 0.276, "xwoba": 0.0, "woba_diff": 0.276, "barrel_pct": 0.0, "hard_hit": 0.0, "exit_velo": 0.0, "whiff_pct": 0.0}, {"name": "", "pa": 313, "era": 3.96, "xera": -0.942, "era_diff": 4.9, "woba": 0.309, "xwoba": 0.0, "woba_diff": 0.309, "barrel_pct": 0.0, "hard_hit": 0.0, "exit_velo": 0.0, "whiff_pct": 0.0}, {"name": "", "pa": 128, "era": 2.11, "xera": -0.936, "era_diff": 3.05, "woba": 0.227, "xwoba": 0.0, "woba_diff": 0.227, "barrel_pct": 0.0, "hard_hit": 0.0, "exit_velo": 0.0, "whiff_pct": 0.0}, {"name": "", "pa": 156, "era": 3.28, "xera": -0.932, "era_diff": 4.21, "woba": 0.283, "xwoba": 0.0, "woba_diff": 0.283, "barrel_pct": 0.0, "hard_hit": 0.0, "exit_velo": 0.0, "whiff_pct": 0.0}, {"name": "", "pa": 223, "era": 4.7, "xera": -0.927, "era_diff": 5.63, "woba": 0.334, "xwoba": 0.0, "woba_diff": 0.334, "barrel_pct": 0.0, "hard_hit": 0.0, "exit_velo": 0.0, "whiff_pct": 0.0}, {"name": "", "pa": 161, "era": 4.42, "xera": -0.926, "era_diff": 5.35, "woba": 0.325, "xwoba": 0.0, "woba_diff": 0.325, "barrel_pct": 0.0, "hard_hit": 0.0, "exit_velo": 0.0, "whiff_pct": 0.0}, {"name": "", "pa": 190, "era": 4.07, "xera": -0.924, "era_diff": 4.99, "woba": 0.313, "xwoba": 0.0, "woba_diff": 0.313, "barrel_pct": 0.0, "hard_hit": 0.0, "exit_velo": 0.0, "whiff_pct": 0.0}, {"name": "", "pa": 256, "era": 5.23, "xera": -0.914, "era_diff": 6.14, "woba": 0.35, "xwoba": 0.0, "woba_diff": 0.35, "barrel_pct": 0.0, "hard_hit": 0.0, "exit_velo": 0.0, "whiff_pct": 0.0}, {"name": "", "pa": 136, "era": 3.23, "xera": -0.882, "era_diff": 4.11, "woba": 0.281, "xwoba": 0.0, "woba_diff": 0.281, "barrel_pct": 0.0, "hard_hit": 0.0, "exit_velo": 0.0, "whiff_pct": 0.0}, {"name": "", "pa": 218, "era": 4.02, "xera": -0.88, "era_diff": 4.9, "woba": 0.311, "xwoba": 0.0, "woba_diff": 0.311, "barrel_pct": 0.0, "hard_hit": 0.0, "exit_velo": 0.0, "whiff_pct": 0.0}, {"name": "", "pa": 235, "era": 3.66, "xera": -0.879, "era_diff": 4.54, "woba": 0.298, "xwoba": 0.0, "woba_diff": 0.298, "barrel_pct": 0.0, "hard_hit": 0.0, "exit_velo": 0.0, "whiff_pct": 0.0}, {"name": "", "pa": 178, "era": 3.82, "xera": -0.867, "era_diff": 4.69, "woba": 0.304, "xwoba": 0.0, "woba_diff": 0.304, "barrel_pct": 0.0, "hard_hit": 0.0, "exit_velo": 0.0, "whiff_pct": 0.0}, {"name": "", "pa": 131, "era": 2.49, "xera": -0.862, "era_diff": 3.35, "woba": 0.247, "xwoba": 0.0, "woba_diff": 0.247, "barrel_pct": 0.0, "hard_hit": 0.0, "exit_velo": 0.0, "whiff_pct": 0.0}, {"name": "", "pa": 165, "era": 4.39, "xera": -0.837, "era_diff": 5.23, "woba": 0.324, "xwoba": 0.0, "woba_diff": 0.324, "barrel_pct": 0.0, "hard_hit": 0.0, "exit_velo": 0.0, "whiff_pct": 0.0}, {"name": "", "pa": 202, "era": 4.27, "xera": -0.834, "era_diff": 5.1, "woba": 0.32, "xwoba": 0.0, "woba_diff": 0.32, "barrel_pct": 0.0, "hard_hit": 0.0, "exit_velo": 0.0, "whiff_pct": 0.0}, {"name": "", "pa": 171, "era": 2.76, "xera": -0.831, "era_diff": 3.59, "woba": 0.26, "xwoba": 0.0, "woba_diff": 0.26, "barrel_pct": 0.0, "hard_hit": 0.0, "exit_velo": 0.0, "whiff_pct": 0.0}, {"name": "", "pa": 233, "era": 3.31, "xera": -0.826, "era_diff": 4.14, "woba": 0.284, "xwoba": 0.0, "woba_diff": 0.284, "barrel_pct": 0.0, "hard_hit": 0.0, "exit_velo": 0.0, "whiff_pct": 0.0}, {"name": "", "pa": 202, "era": 3.33, "xera": -0.813, "era_diff": 4.14, "woba": 0.285, "xwoba": 0.0, "woba_diff": 0.285, "barrel_pct": 0.0, "hard_hit": 0.0, "exit_velo": 0.0, "whiff_pct": 0.0}, {"name": "", "pa": 499, "era": 4.33, "xera": -0.799, "era_diff": 5.13, "woba": 0.322, "xwoba": 0.0, "woba_diff": 0.322, "barrel_pct": 0.0, "hard_hit": 0.0, "exit_velo": 0.0, "whiff_pct": 0.0}, {"name": "", "pa": 346, "era": 4.3, "xera": -0.785, "era_diff": 5.08, "woba": 0.321, "xwoba": 0.0, "woba_diff": 0.321, "barrel_pct": 0.0, "hard_hit": 0.0, "exit_velo": 0.0, "whiff_pct": 0.0}, {"name": "", "pa": 142, "era": 4.16, "xera": -0.785, "era_diff": 4.95, "woba": 0.316, "xwoba": 0.0, "woba_diff": 0.316, "barrel_pct": 0.0, "hard_hit": 0.0, "exit_velo": 0.0, "whiff_pct": 0.0}, {"name": "", "pa": 174, "era": 2.98, "xera": -0.761, "era_diff": 3.74, "woba": 0.27, "xwoba": 0.0, "woba_diff": 0.27, "barrel_pct": 0.0, "hard_hit": 0.0, "exit_velo": 0.0, "whiff_pct": 0.0}, {"name": "", "pa": 393, "era": 4.96, "xera": -0.739, "era_diff": 5.7, "woba": 0.342, "xwoba": 0.0, "woba_diff": 0.342, "barrel_pct": 0.0, "hard_hit": 0.0, "exit_velo": 0.0, "whiff_pct": 0.0}, {"name": "", "pa": 173, "era": 2.8, "xera": -0.733, "era_diff": 3.53, "woba": 0.262, "xwoba": 0.0, "woba_diff": 0.262, "barrel_pct": 0.0, "hard_hit": 0.0, "exit_velo": 0.0, "whiff_pct": 0.0}, {"name": "", "pa": 443, "era": 3.43, "xera": -0.73, "era_diff": 4.16, "woba": 0.289, "xwoba": 0.0, "woba_diff": 0.289, "barrel_pct": 0.0, "hard_hit": 0.0, "exit_velo": 0.0, "whiff_pct": 0.0}, {"name": "", "pa": 209, "era": 3.36, "xera": -0.729, "era_diff": 4.09, "woba": 0.286, "xwoba": 0.0, "woba_diff": 0.286, "barrel_pct": 0.0, "hard_hit": 0.0, "exit_velo": 0.0, "whiff_pct": 0.0}, {"name": "", "pa": 380, "era": 4.04, "xera": -0.728, "era_diff": 4.77, "woba": 0.312, "xwoba": 0.0, "woba_diff": 0.312, "barrel_pct": 0.0, "hard_hit": 0.0, "exit_velo": 0.0, "whiff_pct": 0.0}, {"name": "", "pa": 416, "era": 3.48, "xera": -0.72, "era_diff": 4.2, "woba": 0.291, "xwoba": 0.0, "woba_diff": 0.291, "barrel_pct": 0.0, "hard_hit": 0.0, "exit_velo": 0.0, "whiff_pct": 0.0}, {"name": "", "pa": 195, "era": 3.43, "xera": -0.717, "era_diff": 4.15, "woba": 0.289, "xwoba": 0.0, "woba_diff": 0.289, "barrel_pct": 0.0, "hard_hit": 0.0, "exit_velo": 0.0, "whiff_pct": 0.0}, {"name": "", "pa": 193, "era": 3.79, "xera": -0.716, "era_diff": 4.51, "woba": 0.303, "xwoba": 0.0, "woba_diff": 0.303, "barrel_pct": 0.0, "hard_hit": 0.0, "exit_velo": 0.0, "whiff_pct": 0.0}, {"name": "", "pa": 459, "era": 3.14, "xera": -0.712, "era_diff": 3.85, "woba": 0.277, "xwoba": 0.0, "woba_diff": 0.277, "barrel_pct": 0.0, "hard_hit": 0.0, "exit_velo": 0.0, "whiff_pct": 0.0}, {"name": "", "pa": 184, "era": 3.02, "xera": -0.709, "era_diff": 3.73, "woba": 0.272, "xwoba": 0.0, "woba_diff": 0.272, "barrel_pct": 0.0, "hard_hit": 0.0, "exit_velo": 0.0, "whiff_pct": 0.0}, {"name": "", "pa": 150, "era": 4.93, "xera": -0.706, "era_diff": 5.64, "woba": 0.341, "xwoba": 0.0, "woba_diff": 0.341, "barrel_pct": 0.0, "hard_hit": 0.0, "exit_velo": 0.0, "whiff_pct": 0.0}, {"name": "", "pa": 296, "era": 3.88, "xera": -0.698, "era_diff": 4.58, "woba": 0.306, "xwoba": 0.0, "woba_diff": 0.306, "barrel_pct": 0.0, "hard_hit": 0.0, "exit_velo": 0.0, "whiff_pct": 0.0}, {"name": "", "pa": 401, "era": 4.99, "xera": -0.695, "era_diff": 5.69, "woba": 0.343, "xwoba": 0.0, "woba_diff": 0.343, "barrel_pct": 0.0, "hard_hit": 0.0, "exit_velo": 0.0, "whiff_pct": 0.0}, {"name": "", "pa": 489, "era": 3.56, "xera": -0.692, "era_diff": 4.25, "woba": 0.294, "xwoba": 0.0, "woba_diff": 0.294, "barrel_pct": 0.0, "hard_hit": 0.0, "exit_velo": 0.0, "whiff_pct": 0.0}, {"name": "", "pa": 242, "era": 2.67, "xera": -0.692, "era_diff": 3.36, "woba": 0.256, "xwoba": 0.0, "woba_diff": 0.256, "barrel_pct": 0.0, "hard_hit": 0.0, "exit_velo": 0.0, "whiff_pct": 0.0}, {"name": "", "pa": 176, "era": 3.66, "xera": -0.689, "era_diff": 4.35, "woba": 0.298, "xwoba": 0.0, "woba_diff": 0.298, "barrel_pct": 0.0, "hard_hit": 0.0, "exit_velo": 0.0, "whiff_pct": 0.0}, {"name": "", "pa": 482, "era": 4.9, "xera": -0.687, "era_diff": 5.59, "woba": 0.34, "xwoba": 0.0, "woba_diff": 0.34, "barrel_pct": 0.0, "hard_hit": 0.0, "exit_velo": 0.0, "whiff_pct": 0.0}, {"name": "", "pa": 469, "era": 2.65, "xera": -0.684, "era_diff": 3.33, "woba": 0.255, "xwoba": 0.0, "woba_diff": 0.255, "barrel_pct": 0.0, "hard_hit": 0.0, "exit_velo": 0.0, "whiff_pct": 0.0}, {"name": "", "pa": 214, "era": 4.33, "xera": -0.675, "era_diff": 5.0, "woba": 0.322, "xwoba": 0.0, "woba_diff": 0.322, "barrel_pct": 0.0, "hard_hit": 0.0, "exit_velo": 0.0, "whiff_pct": 0.0}, {"name": "", "pa": 178, "era": 3.85, "xera": -0.649, "era_diff": 4.5, "woba": 0.305, "xwoba": 0.0, "woba_diff": 0.305, "barrel_pct": 0.0, "hard_hit": 0.0, "exit_velo": 0.0, "whiff_pct": 0.0}, {"name": "", "pa": 531, "era": 4.16, "xera": -0.638, "era_diff": 4.8, "woba": 0.316, "xwoba": 0.0, "woba_diff": 0.316, "barrel_pct": 0.0, "hard_hit": 0.0, "exit_velo": 0.0, "whiff_pct": 0.0}, {"name": "", "pa": 497, "era": 4.8, "xera": -0.625, "era_diff": 5.42, "woba": 0.337, "xwoba": 0.0, "woba_diff": 0.337, "barrel_pct": 0.0, "hard_hit": 0.0, "exit_velo": 0.0, "whiff_pct": 0.0}, {"name": "", "pa": 191, "era": 4.51, "xera": -0.614, "era_diff": 5.12, "woba": 0.328, "xwoba": 0.0, "woba_diff": 0.328, "barrel_pct": 0.0, "hard_hit": 0.0, "exit_velo": 0.0, "whiff_pct": 0.0}, {"name": "", "pa": 285, "era": 5.51, "xera": -0.61, "era_diff": 6.12, "woba": 0.358, "xwoba": 0.0, "woba_diff": 0.358, "barrel_pct": 0.0, "hard_hit": 0.0, "exit_velo": 0.0, "whiff_pct": 0.0}, {"name": "", "pa": 197, "era": 3.43, "xera": -0.609, "era_diff": 4.04, "woba": 0.289, "xwoba": 0.0, "woba_diff": 0.289, "barrel_pct": 0.0, "hard_hit": 0.0, "exit_velo": 0.0, "whiff_pct": 0.0}, {"name": "", "pa": 318, "era": 3.16, "xera": -0.607, "era_diff": 3.77, "woba": 0.278, "xwoba": 0.0, "woba_diff": 0.278, "barrel_pct": 0.0, "hard_hit": 0.0, "exit_velo": 0.0, "whiff_pct": 0.0}, {"name": "", "pa": 278, "era": 5.7, "xera": -0.598, "era_diff": 6.3, "woba": 0.363, "xwoba": 0.0, "woba_diff": 0.363, "barrel_pct": 0.0, "hard_hit": 0.0, "exit_velo": 0.0, "whiff_pct": 0.0}, {"name": "", "pa": 485, "era": 4.55, "xera": -0.596, "era_diff": 5.15, "woba": 0.329, "xwoba": 0.0, "woba_diff": 0.329, "barrel_pct": 0.0, "hard_hit": 0.0, "exit_velo": 0.0, "whiff_pct": 0.0}, {"name": "", "pa": 426, "era": 4.45, "xera": -0.593, "era_diff": 5.04, "woba": 0.326, "xwoba": 0.0, "woba_diff": 0.326, "barrel_pct": 0.0, "hard_hit": 0.0, "exit_velo": 0.0, "whiff_pct": 0.0}, {"name": "", "pa": 159, "era": 3.64, "xera": -0.589, "era_diff": 4.23, "woba": 0.297, "xwoba": 0.0, "woba_diff": 0.297, "barrel_pct": 0.0, "hard_hit": 0.0, "exit_velo": 0.0, "whiff_pct": 0.0}, {"name": "", "pa": 266, "era": 5.23, "xera": -0.582, "era_diff": 5.81, "woba": 0.35, "xwoba": 0.0, "woba_diff": 0.35, "barrel_pct": 0.0, "hard_hit": 0.0, "exit_velo": 0.0, "whiff_pct": 0.0}, {"name": "", "pa": 308, "era": 4.55, "xera": -0.559, "era_diff": 5.11, "woba": 0.329, "xwoba": 0.0, "woba_diff": 0.329, "barrel_pct": 0.0, "hard_hit": 0.0, "exit_velo": 0.0, "whiff_pct": 0.0}, {"name": "", "pa": 179, "era": 3.66, "xera": -0.555, "era_diff": 4.21, "woba": 0.298, "xwoba": 0.0, "woba_diff": 0.298, "barrel_pct": 0.0, "hard_hit": 0.0, "exit_velo": 0.0, "whiff_pct": 0.0}, {"name": "", "pa": 199, "era": 2.63, "xera": -0.553, "era_diff": 3.18, "woba": 0.254, "xwoba": 0.0, "woba_diff": 0.254, "barrel_pct": 0.0, "hard_hit": 0.0, "exit_velo": 0.0, "whiff_pct": 0.0}, {"name": "", "pa": 587, "era": 4.36, "xera": -0.551, "era_diff": 4.91, "woba": 0.323, "xwoba": 0.0, "woba_diff": 0.323, "barrel_pct": 0.0, "hard_hit": 0.0, "exit_velo": 0.0, "whiff_pct": 0.0}, {"name": "", "pa": 188, "era": 4.48, "xera": -0.55, "era_diff": 5.03, "woba": 0.327, "xwoba": 0.0, "woba_diff": 0.327, "barrel_pct": 0.0, "hard_hit": 0.0, "exit_velo": 0.0, "whiff_pct": 0.0}, {"name": "", "pa": 173, "era": 2.8, "xera": -0.55, "era_diff": 3.35, "woba": 0.262, "xwoba": 0.0, "woba_diff": 0.262, "barrel_pct": 0.0, "hard_hit": 0.0, "exit_velo": 0.0, "whiff_pct": 0.0}, {"name": "", "pa": 145, "era": 2.84, "xera": -0.542, "era_diff": 3.38, "woba": 0.264, "xwoba": 0.0, "woba_diff": 0.264, "barrel_pct": 0.0, "hard_hit": 0.0, "exit_velo": 0.0, "whiff_pct": 0.0}, {"name": "", "pa": 442, "era": 3.93, "xera": -0.54, "era_diff": 4.47, "woba": 0.308, "xwoba": 0.0, "woba_diff": 0.308, "barrel_pct": 0.0, "hard_hit": 0.0, "exit_velo": 0.0, "whiff_pct": 0.0}, {"name": "", "pa": 513, "era": 3.74, "xera": -0.534, "era_diff": 4.27, "woba": 0.301, "xwoba": 0.0, "woba_diff": 0.301, "barrel_pct": 0.0, "hard_hit": 0.0, "exit_velo": 0.0, "whiff_pct": 0.0}, {"name": "", "pa": 545, "era": 3.02, "xera": -0.525, "era_diff": 3.54, "woba": 0.272, "xwoba": 0.0, "woba_diff": 0.272, "barrel_pct": 0.0, "hard_hit": 0.0, "exit_velo": 0.0, "whiff_pct": 0.0}, {"name": "", "pa": 299, "era": 4.07, "xera": -0.525, "era_diff": 4.6, "woba": 0.313, "xwoba": 0.0, "woba_diff": 0.313, "barrel_pct": 0.0, "hard_hit": 0.0, "exit_velo": 0.0, "whiff_pct": 0.0}, {"name": "", "pa": 551, "era": 3.38, "xera": -0.523, "era_diff": 3.9, "woba": 0.287, "xwoba": 0.0, "woba_diff": 0.287, "barrel_pct": 0.0, "hard_hit": 0.0, "exit_velo": 0.0, "whiff_pct": 0.0}, {"name": "", "pa": 197, "era": 4.42, "xera": -0.52, "era_diff": 4.94, "woba": 0.325, "xwoba": 0.0, "woba_diff": 0.325, "barrel_pct": 0.0, "hard_hit": 0.0, "exit_velo": 0.0, "whiff_pct": 0.0}, {"name": "", "pa": 373, "era": 4.04, "xera": -0.51, "era_diff": 4.55, "woba": 0.312, "xwoba": 0.0, "woba_diff": 0.312, "barrel_pct": 0.0, "hard_hit": 0.0, "exit_velo": 0.0, "whiff_pct": 0.0}, {"name": "", "pa": 435, "era": 5.06, "xera": -0.505, "era_diff": 5.56, "woba": 0.345, "xwoba": 0.0, "woba_diff": 0.345, "barrel_pct": 0.0, "hard_hit": 0.0, "exit_velo": 0.0, "whiff_pct": 0.0}, {"name": "", "pa": 406, "era": 4.58, "xera": -0.505, "era_diff": 5.08, "woba": 0.33, "xwoba": 0.0, "woba_diff": 0.33, "barrel_pct": 0.0, "hard_hit": 0.0, "exit_velo": 0.0, "whiff_pct": 0.0}, {"name": "", "pa": 530, "era": 4.04, "xera": -0.503, "era_diff": 4.54, "woba": 0.312, "xwoba": 0.0, "woba_diff": 0.312, "barrel_pct": 0.0, "hard_hit": 0.0, "exit_velo": 0.0, "whiff_pct": 0.0}, {"name": "", "pa": 251, "era": 3.71, "xera": -0.5, "era_diff": 4.21, "woba": 0.3, "xwoba": 0.0, "woba_diff": 0.3, "barrel_pct": 0.0, "hard_hit": 0.0, "exit_velo": 0.0, "whiff_pct": 0.0}, {"name": "", "pa": 469, "era": 2.71, "xera": -0.498, "era_diff": 3.21, "woba": 0.258, "xwoba": 0.0, "woba_diff": 0.258, "barrel_pct": 0.0, "hard_hit": 0.0, "exit_velo": 0.0, "whiff_pct": 0.0}, {"name": "", "pa": 521, "era": 4.48, "xera": -0.493, "era_diff": 4.97, "woba": 0.327, "xwoba": 0.0, "woba_diff": 0.327, "barrel_pct": 0.0, "hard_hit": 0.0, "exit_velo": 0.0, "whiff_pct": 0.0}, {"name": "", "pa": 400, "era": 5.41, "xera": -0.481, "era_diff": 5.89, "woba": 0.355, "xwoba": 0.0, "woba_diff": 0.355, "barrel_pct": 0.0, "hard_hit": 0.0, "exit_velo": 0.0, "whiff_pct": 0.0}, {"name": "", "pa": 194, "era": 3.71, "xera": -0.48, "era_diff": 4.19, "woba": 0.3, "xwoba": 0.0, "woba_diff": 0.3, "barrel_pct": 0.0, "hard_hit": 0.0, "exit_velo": 0.0, "whiff_pct": 0.0}, {"name": "", "pa": 349, "era": 4.93, "xera": -0.478, "era_diff": 5.41, "woba": 0.341, "xwoba": 0.0, "woba_diff": 0.341, "barrel_pct": 0.0, "hard_hit": 0.0, "exit_velo": 0.0, "whiff_pct": 0.0}, {"name": "", "pa": 306, "era": 3.56, "xera": -0.47, "era_diff": 4.03, "woba": 0.294, "xwoba": 0.0, "woba_diff": 0.294, "barrel_pct": 0.0, "hard_hit": 0.0, "exit_velo": 0.0, "whiff_pct": 0.0}, {"name": "", "pa": 185, "era": 2.51, "xera": -0.453, "era_diff": 2.96, "woba": 0.248, "xwoba": 0.0, "woba_diff": 0.248, "barrel_pct": 0.0, "hard_hit": 0.0, "exit_velo": 0.0, "whiff_pct": 0.0}, {"name": "", "pa": 390, "era": 4.9, "xera": -0.448, "era_diff": 5.35, "woba": 0.34, "xwoba": 0.0, "woba_diff": 0.34, "barrel_pct": 0.0, "hard_hit": 0.0, "exit_velo": 0.0, "whiff_pct": 0.0}, {"name": "", "pa": 326, "era": 4.24, "xera": -0.443, "era_diff": 4.68, "woba": 0.319, "xwoba": 0.0, "woba_diff": 0.319, "barrel_pct": 0.0, "hard_hit": 0.0, "exit_velo": 0.0, "whiff_pct": 0.0}, {"name": "", "pa": 342, "era": 3.79, "xera": -0.435, "era_diff": 4.22, "woba": 0.303, "xwoba": 0.0, "woba_diff": 0.303, "barrel_pct": 0.0, "hard_hit": 0.0, "exit_velo": 0.0, "whiff_pct": 0.0}, {"name": "", "pa": 529, "era": 5.27, "xera": -0.434, "era_diff": 5.7, "woba": 0.351, "xwoba": 0.0, "woba_diff": 0.351, "barrel_pct": 0.0, "hard_hit": 0.0, "exit_velo": 0.0, "whiff_pct": 0.0}, {"name": "", "pa": 184, "era": 3.79, "xera": -0.433, "era_diff": 4.22, "woba": 0.303, "xwoba": 0.0, "woba_diff": 0.303, "barrel_pct": 0.0, "hard_hit": 0.0, "exit_velo": 0.0, "whiff_pct": 0.0}, {"name": "", "pa": 171, "era": 3.61, "xera": -0.425, "era_diff": 4.04, "woba": 0.296, "xwoba": 0.0, "woba_diff": 0.296, "barrel_pct": 0.0, "hard_hit": 0.0, "exit_velo": 0.0, "whiff_pct": 0.0}, {"name": "", "pa": 156, "era": 4.22, "xera": -0.41, "era_diff": 4.63, "woba": 0.318, "xwoba": 0.0, "woba_diff": 0.318, "barrel_pct": 0.0, "hard_hit": 0.0, "exit_velo": 0.0, "whiff_pct": 0.0}, {"name": "", "pa": 152, "era": 3.66, "xera": -0.407, "era_diff": 4.07, "woba": 0.298, "xwoba": 0.0, "woba_diff": 0.298, "barrel_pct": 0.0, "hard_hit": 0.0, "exit_velo": 0.0, "whiff_pct": 0.0}, {"name": "", "pa": 243, "era": 4.77, "xera": -0.405, "era_diff": 5.17, "woba": 0.336, "xwoba": 0.0, "woba_diff": 0.336, "barrel_pct": 0.0, "hard_hit": 0.0, "exit_velo": 0.0, "whiff_pct": 0.0}, {"name": "", "pa": 500, "era": 4.61, "xera": -0.395, "era_diff": 5.01, "woba": 0.331, "xwoba": 0.0, "woba_diff": 0.331, "barrel_pct": 0.0, "hard_hit": 0.0, "exit_velo": 0.0, "whiff_pct": 0.0}, {"name": "", "pa": 269, "era": 4.33, "xera": -0.392, "era_diff": 4.72, "woba": 0.322, "xwoba": 0.0, "woba_diff": 0.322, "barrel_pct": 0.0, "hard_hit": 0.0, "exit_velo": 0.0, "whiff_pct": 0.0}, {"name": "", "pa": 467, "era": 4.24, "xera": -0.391, "era_diff": 4.63, "woba": 0.319, "xwoba": 0.0, "woba_diff": 0.319, "barrel_pct": 0.0, "hard_hit": 0.0, "exit_velo": 0.0, "whiff_pct": 0.0}, {"name": "", "pa": 392, "era": 4.73, "xera": -0.391, "era_diff": 5.12, "woba": 0.335, "xwoba": 0.0, "woba_diff": 0.335, "barrel_pct": 0.0, "hard_hit": 0.0, "exit_velo": 0.0, "whiff_pct": 0.0}, {"name": "", "pa": 444, "era": 3.36, "xera": -0.389, "era_diff": 3.75, "woba": 0.286, "xwoba": 0.0, "woba_diff": 0.286, "barrel_pct": 0.0, "hard_hit": 0.0, "exit_velo": 0.0, "whiff_pct": 0.0}, {"name": "", "pa": 174, "era": 3.96, "xera": -0.389, "era_diff": 4.35, "woba": 0.309, "xwoba": 0.0, "woba_diff": 0.309, "barrel_pct": 0.0, "hard_hit": 0.0, "exit_velo": 0.0, "whiff_pct": 0.0}, {"name": "", "pa": 478, "era": 4.77, "xera": -0.367, "era_diff": 5.14, "woba": 0.336, "xwoba": 0.0, "woba_diff": 0.336, "barrel_pct": 0.0, "hard_hit": 0.0, "exit_velo": 0.0, "whiff_pct": 0.0}, {"name": "", "pa": 579, "era": 3.58, "xera": -0.363, "era_diff": 3.94, "woba": 0.295, "xwoba": 0.0, "woba_diff": 0.295, "barrel_pct": 0.0, "hard_hit": 0.0, "exit_velo": 0.0, "whiff_pct": 0.0}, {"name": "", "pa": 170, "era": 3.66, "xera": -0.36, "era_diff": 4.02, "woba": 0.298, "xwoba": 0.0, "woba_diff": 0.298, "barrel_pct": 0.0, "hard_hit": 0.0, "exit_velo": 0.0, "whiff_pct": 0.0}, {"name": "", "pa": 136, "era": 3.26, "xera": -0.355, "era_diff": 3.61, "woba": 0.282, "xwoba": 0.0, "woba_diff": 0.282, "barrel_pct": 0.0, "hard_hit": 0.0, "exit_velo": 0.0, "whiff_pct": 0.0}, {"name": "", "pa": 165, "era": 3.77, "xera": -0.354, "era_diff": 4.12, "woba": 0.302, "xwoba": 0.0, "woba_diff": 0.302, "barrel_pct": 0.0, "hard_hit": 0.0, "exit_velo": 0.0, "whiff_pct": 0.0}, {"name": "", "pa": 332, "era": 3.88, "xera": -0.345, "era_diff": 4.22, "woba": 0.306, "xwoba": 0.0, "woba_diff": 0.306, "barrel_pct": 0.0, "hard_hit": 0.0, "exit_velo": 0.0, "whiff_pct": 0.0}, {"name": "", "pa": 465, "era": 3.66, "xera": -0.342, "era_diff": 4.0, "woba": 0.298, "xwoba": 0.0, "woba_diff": 0.298, "barrel_pct": 0.0, "hard_hit": 0.0, "exit_velo": 0.0, "whiff_pct": 0.0}, {"name": "", "pa": 423, "era": 4.07, "xera": -0.337, "era_diff": 4.41, "woba": 0.313, "xwoba": 0.0, "woba_diff": 0.313, "barrel_pct": 0.0, "hard_hit": 0.0, "exit_velo": 0.0, "whiff_pct": 0.0}, {"name": "", "pa": 489, "era": 6.98, "xera": -0.334, "era_diff": 7.31, "woba": 0.395, "xwoba": 0.0, "woba_diff": 0.395, "barrel_pct": 0.0, "hard_hit": 0.0, "exit_velo": 0.0, "whiff_pct": 0.0}, {"name": "", "pa": 540, "era": 4.19, "xera": -0.333, "era_diff": 4.52, "woba": 0.317, "xwoba": 0.0, "woba_diff": 0.317, "barrel_pct": 0.0, "hard_hit": 0.0, "exit_velo": 0.0, "whiff_pct": 0.0}, {"name": "", "pa": 157, "era": 3.36, "xera": -0.331, "era_diff": 3.69, "woba": 0.286, "xwoba": 0.0, "woba_diff": 0.286, "barrel_pct": 0.0, "hard_hit": 0.0, "exit_velo": 0.0, "whiff_pct": 0.0}, {"name": "", "pa": 237, "era": 3.38, "xera": -0.328, "era_diff": 3.71, "woba": 0.287, "xwoba": 0.0, "woba_diff": 0.287, "barrel_pct": 0.0, "hard_hit": 0.0, "exit_velo": 0.0, "whiff_pct": 0.0}, {"name": "", "pa": 215, "era": 3.41, "xera": -0.32, "era_diff": 3.73, "woba": 0.288, "xwoba": 0.0, "woba_diff": 0.288, "barrel_pct": 0.0, "hard_hit": 0.0, "exit_velo": 0.0, "whiff_pct": 0.0}, {"name": "", "pa": 509, "era": 2.89, "xera": -0.304, "era_diff": 3.19, "woba": 0.266, "xwoba": 0.0, "woba_diff": 0.266, "barrel_pct": 0.0, "hard_hit": 0.0, "exit_velo": 0.0, "whiff_pct": 0.0}, {"name": "", "pa": 284, "era": 4.67, "xera": -0.302, "era_diff": 4.97, "woba": 0.333, "xwoba": 0.0, "woba_diff": 0.333, "barrel_pct": 0.0, "hard_hit": 0.0, "exit_velo": 0.0, "whiff_pct": 0.0}, {"name": "", "pa": 156, "era": 3.93, "xera": -0.298, "era_diff": 4.23, "woba": 0.308, "xwoba": 0.0, "woba_diff": 0.308, "barrel_pct": 0.0, "hard_hit": 0.0, "exit_velo": 0.0, "whiff_pct": 0.0}, {"name": "", "pa": 302, "era": 2.87, "xera": -0.292, "era_diff": 3.16, "woba": 0.265, "xwoba": 0.0, "woba_diff": 0.265, "barrel_pct": 0.0, "hard_hit": 0.0, "exit_velo": 0.0, "whiff_pct": 0.0}, {"name": "", "pa": 260, "era": 3.05, "xera": -0.291, "era_diff": 3.34, "woba": 0.273, "xwoba": 0.0, "woba_diff": 0.273, "barrel_pct": 0.0, "hard_hit": 0.0, "exit_velo": 0.0, "whiff_pct": 0.0}, {"name": "", "pa": 191, "era": 3.07, "xera": -0.291, "era_diff": 3.36, "woba": 0.274, "xwoba": 0.0, "woba_diff": 0.274, "barrel_pct": 0.0, "hard_hit": 0.0, "exit_velo": 0.0, "whiff_pct": 0.0}, {"name": "", "pa": 353, "era": 4.45, "xera": -0.277, "era_diff": 4.73, "woba": 0.326, "xwoba": 0.0, "woba_diff": 0.326, "barrel_pct": 0.0, "hard_hit": 0.0, "exit_velo": 0.0, "whiff_pct": 0.0}, {"name": "", "pa": 560, "era": 5.96, "xera": -0.276, "era_diff": 6.24, "woba": 0.37, "xwoba": 0.0, "woba_diff": 0.37, "barrel_pct": 0.0, "hard_hit": 0.0, "exit_velo": 0.0, "whiff_pct": 0.0}, {"name": "", "pa": 504, "era": 3.36, "xera": -0.273, "era_diff": 3.63, "woba": 0.286, "xwoba": 0.0, "woba_diff": 0.286, "barrel_pct": 0.0, "hard_hit": 0.0, "exit_velo": 0.0, "whiff_pct": 0.0}, {"name": "", "pa": 537, "era": 4.45, "xera": -0.265, "era_diff": 4.71, "woba": 0.326, "xwoba": 0.0, "woba_diff": 0.326, "barrel_pct": 0.0, "hard_hit": 0.0, "exit_velo": 0.0, "whiff_pct": 0.0}, {"name": "", "pa": 128, "era": 3.61, "xera": -0.258, "era_diff": 3.87, "woba": 0.296, "xwoba": 0.0, "woba_diff": 0.296, "barrel_pct": 0.0, "hard_hit": 0.0, "exit_velo": 0.0, "whiff_pct": 0.0}, {"name": "", "pa": 166, "era": 3.09, "xera": -0.256, "era_diff": 3.35, "woba": 0.275, "xwoba": 0.0, "woba_diff": 0.275, "barrel_pct": 0.0, "hard_hit": 0.0, "exit_velo": 0.0, "whiff_pct": 0.0}, {"name": "", "pa": 421, "era": 2.74, "xera": -0.252, "era_diff": 2.99, "woba": 0.259, "xwoba": 0.0, "woba_diff": 0.259, "barrel_pct": 0.0, "hard_hit": 0.0, "exit_velo": 0.0, "whiff_pct": 0.0}, {"name": "", "pa": 319, "era": 4.67, "xera": -0.248, "era_diff": 4.92, "woba": 0.333, "xwoba": 0.0, "woba_diff": 0.333, "barrel_pct": 0.0, "hard_hit": 0.0, "exit_velo": 0.0, "whiff_pct": 0.0}, {"name": "", "pa": 151, "era": 3.38, "xera": -0.245, "era_diff": 3.62, "woba": 0.287, "xwoba": 0.0, "woba_diff": 0.287, "barrel_pct": 0.0, "hard_hit": 0.0, "exit_velo": 0.0, "whiff_pct": 0.0}, {"name": "", "pa": 150, "era": 4.3, "xera": -0.241, "era_diff": 4.54, "woba": 0.321, "xwoba": 0.0, "woba_diff": 0.321, "barrel_pct": 0.0, "hard_hit": 0.0, "exit_velo": 0.0, "whiff_pct": 0.0}, {"name": "", "pa": 479, "era": 4.27, "xera": -0.239, "era_diff": 4.51, "woba": 0.32, "xwoba": 0.0, "woba_diff": 0.32, "barrel_pct": 0.0, "hard_hit": 0.0, "exit_velo": 0.0, "whiff_pct": 0.0}, {"name": "", "pa": 393, "era": 5.2, "xera": -0.235, "era_diff": 5.44, "woba": 0.349, "xwoba": 0.0, "woba_diff": 0.349, "barrel_pct": 0.0, "hard_hit": 0.0, "exit_velo": 0.0, "whiff_pct": 0.0}, {"name": "", "pa": 326, "era": 5.44, "xera": -0.232, "era_diff": 5.67, "woba": 0.356, "xwoba": 0.0, "woba_diff": 0.356, "barrel_pct": 0.0, "hard_hit": 0.0, "exit_velo": 0.0, "whiff_pct": 0.0}, {"name": "", "pa": 188, "era": 3.23, "xera": -0.23, "era_diff": 3.46, "woba": 0.281, "xwoba": 0.0, "woba_diff": 0.281, "barrel_pct": 0.0, "hard_hit": 0.0, "exit_velo": 0.0, "whiff_pct": 0.0}, {"name": "", "pa": 183, "era": 4.02, "xera": -0.223, "era_diff": 4.24, "woba": 0.311, "xwoba": 0.0, "woba_diff": 0.311, "barrel_pct": 0.0, "hard_hit": 0.0, "exit_velo": 0.0, "whiff_pct": 0.0}, {"name": "", "pa": 146, "era": 4.48, "xera": -0.208, "era_diff": 4.69, "woba": 0.327, "xwoba": 0.0, "woba_diff": 0.327, "barrel_pct": 0.0, "hard_hit": 0.0, "exit_velo": 0.0, "whiff_pct": 0.0}, {"name": "", "pa": 485, "era": 4.45, "xera": -0.199, "era_diff": 4.65, "woba": 0.326, "xwoba": 0.0, "woba_diff": 0.326, "barrel_pct": 0.0, "hard_hit": 0.0, "exit_velo": 0.0, "whiff_pct": 0.0}, {"name": "", "pa": 505, "era": 4.16, "xera": -0.197, "era_diff": 4.36, "woba": 0.316, "xwoba": 0.0, "woba_diff": 0.316, "barrel_pct": 0.0, "hard_hit": 0.0, "exit_velo": 0.0, "whiff_pct": 0.0}, {"name": "", "pa": 518, "era": 4.3, "xera": -0.195, "era_diff": 4.5, "woba": 0.321, "xwoba": 0.0, "woba_diff": 0.321, "barrel_pct": 0.0, "hard_hit": 0.0, "exit_velo": 0.0, "whiff_pct": 0.0}, {"name": "", "pa": 140, "era": 4.07, "xera": -0.188, "era_diff": 4.26, "woba": 0.313, "xwoba": 0.0, "woba_diff": 0.313, "barrel_pct": 0.0, "hard_hit": 0.0, "exit_velo": 0.0, "whiff_pct": 0.0}, {"name": "", "pa": 442, "era": 3.51, "xera": -0.178, "era_diff": 3.69, "woba": 0.292, "xwoba": 0.0, "woba_diff": 0.292, "barrel_pct": 0.0, "hard_hit": 0.0, "exit_velo": 0.0, "whiff_pct": 0.0}, {"name": "", "pa": 401, "era": 3.99, "xera": -0.177, "era_diff": 4.17, "woba": 0.31, "xwoba": 0.0, "woba_diff": 0.31, "barrel_pct": 0.0, "hard_hit": 0.0, "exit_velo": 0.0, "whiff_pct": 0.0}, {"name": "", "pa": 178, "era": 3.0, "xera": -0.177, "era_diff": 3.18, "woba": 0.271, "xwoba": 0.0, "woba_diff": 0.271, "barrel_pct": 0.0, "hard_hit": 0.0, "exit_velo": 0.0, "whiff_pct": 0.0}, {"name": "", "pa": 394, "era": 3.85, "xera": -0.171, "era_diff": 4.02, "woba": 0.305, "xwoba": 0.0, "woba_diff": 0.305, "barrel_pct": 0.0, "hard_hit": 0.0, "exit_velo": 0.0, "whiff_pct": 0.0}, {"name": "", "pa": 426, "era": 4.33, "xera": -0.159, "era_diff": 4.49, "woba": 0.322, "xwoba": 0.0, "woba_diff": 0.322, "barrel_pct": 0.0, "hard_hit": 0.0, "exit_velo": 0.0, "whiff_pct": 0.0}, {"name": "", "pa": 445, "era": 4.02, "xera": -0.155, "era_diff": 4.17, "woba": 0.311, "xwoba": 0.0, "woba_diff": 0.311, "barrel_pct": 0.0, "hard_hit": 0.0, "exit_velo": 0.0, "whiff_pct": 0.0}, {"name": "", "pa": 531, "era": 3.74, "xera": -0.149, "era_diff": 3.89, "woba": 0.301, "xwoba": 0.0, "woba_diff": 0.301, "barrel_pct": 0.0, "hard_hit": 0.0, "exit_velo": 0.0, "whiff_pct": 0.0}, {"name": "", "pa": 470, "era": 4.58, "xera": -0.145, "era_diff": 4.72, "woba": 0.33, "xwoba": 0.0, "woba_diff": 0.33, "barrel_pct": 0.0, "hard_hit": 0.0, "exit_velo": 0.0, "whiff_pct": 0.0}, {"name": "", "pa": 177, "era": 4.36, "xera": -0.145, "era_diff": 4.5, "woba": 0.323, "xwoba": 0.0, "woba_diff": 0.323, "barrel_pct": 0.0, "hard_hit": 0.0, "exit_velo": 0.0, "whiff_pct": 0.0}, {"name": "", "pa": 167, "era": 3.33, "xera": -0.145, "era_diff": 3.48, "woba": 0.285, "xwoba": 0.0, "woba_diff": 0.285, "barrel_pct": 0.0, "hard_hit": 0.0, "exit_velo": 0.0, "whiff_pct": 0.0}, {"name": "", "pa": 180, "era": 4.8, "xera": -0.145, "era_diff": 4.94, "woba": 0.337, "xwoba": 0.0, "woba_diff": 0.337, "barrel_pct": 0.0, "hard_hit": 0.0, "exit_velo": 0.0, "whiff_pct": 0.0}, {"name": "", "pa": 401, "era": 5.66, "xera": -0.142, "era_diff": 5.8, "woba": 0.362, "xwoba": 0.0, "woba_diff": 0.362, "barrel_pct": 0.0, "hard_hit": 0.0, "exit_velo": 0.0, "whiff_pct": 0.0}, {"name": "", "pa": 214, "era": 3.33, "xera": -0.142, "era_diff": 3.47, "woba": 0.285, "xwoba": 0.0, "woba_diff": 0.285, "barrel_pct": 0.0, "hard_hit": 0.0, "exit_velo": 0.0, "whiff_pct": 0.0}, {"name": "", "pa": 540, "era": 3.79, "xera": -0.134, "era_diff": 3.92, "woba": 0.303, "xwoba": 0.0, "woba_diff": 0.303, "barrel_pct": 0.0, "hard_hit": 0.0, "exit_velo": 0.0, "whiff_pct": 0.0}, {"name": "", "pa": 493, "era": 3.07, "xera": -0.129, "era_diff": 3.2, "woba": 0.274, "xwoba": 0.0, "woba_diff": 0.274, "barrel_pct": 0.0, "hard_hit": 0.0, "exit_velo": 0.0, "whiff_pct": 0.0}, {"name": "", "pa": 231, "era": 3.79, "xera": -0.129, "era_diff": 3.92, "woba": 0.303, "xwoba": 0.0, "woba_diff": 0.303, "barrel_pct": 0.0, "hard_hit": 0.0, "exit_velo": 0.0, "whiff_pct": 0.0}, {"name": "", "pa": 162, "era": 3.88, "xera": -0.113, "era_diff": 3.99, "woba": 0.306, "xwoba": 0.0, "woba_diff": 0.306, "barrel_pct": 0.0, "hard_hit": 0.0, "exit_velo": 0.0, "whiff_pct": 0.0}, {"name": "", "pa": 252, "era": 4.1, "xera": -0.1, "era_diff": 4.2, "woba": 0.314, "xwoba": 0.0, "woba_diff": 0.314, "barrel_pct": 0.0, "hard_hit": 0.0, "exit_velo": 0.0, "whiff_pct": 0.0}, {"name": "", "pa": 144, "era": 3.26, "xera": -0.1, "era_diff": 3.36, "woba": 0.282, "xwoba": 0.0, "woba_diff": 0.282, "barrel_pct": 0.0, "hard_hit": 0.0, "exit_velo": 0.0, "whiff_pct": 0.0}, {"name": "", "pa": 183, "era": 3.88, "xera": -0.091, "era_diff": 3.97, "woba": 0.306, "xwoba": 0.0, "woba_diff": 0.306, "barrel_pct": 0.0, "hard_hit": 0.0, "exit_velo": 0.0, "whiff_pct": 0.0}, {"name": "", "pa": 177, "era": 4.07, "xera": -0.091, "era_diff": 4.16, "woba": 0.313, "xwoba": 0.0, "woba_diff": 0.313, "barrel_pct": 0.0, "hard_hit": 0.0, "exit_velo": 0.0, "whiff_pct": 0.0}, {"name": "", "pa": 242, "era": 4.86, "xera": -0.088, "era_diff": 4.95, "woba": 0.339, "xwoba": 0.0, "woba_diff": 0.339, "barrel_pct": 0.0, "hard_hit": 0.0, "exit_velo": 0.0, "whiff_pct": 0.0}, {"name": "", "pa": 185, "era": 4.51, "xera": -0.081, "era_diff": 4.59, "woba": 0.328, "xwoba": 0.0, "woba_diff": 0.328, "barrel_pct": 0.0, "hard_hit": 0.0, "exit_velo": 0.0, "whiff_pct": 0.0}, {"name": "", "pa": 515, "era": 4.61, "xera": -0.073, "era_diff": 4.68, "woba": 0.331, "xwoba": 0.0, "woba_diff": 0.331, "barrel_pct": 0.0, "hard_hit": 0.0, "exit_velo": 0.0, "whiff_pct": 0.0}, {"name": "", "pa": 195, "era": 4.8, "xera": -0.068, "era_diff": 4.87, "woba": 0.337, "xwoba": 0.0, "woba_diff": 0.337, "barrel_pct": 0.0, "hard_hit": 0.0, "exit_velo": 0.0, "whiff_pct": 0.0}, {"name": "", "pa": 168, "era": 3.64, "xera": -0.058, "era_diff": 3.7, "woba": 0.297, "xwoba": 0.0, "woba_diff": 0.297, "barrel_pct": 0.0, "hard_hit": 0.0, "exit_velo": 0.0, "whiff_pct": 0.0}, {"name": "", "pa": 492, "era": 3.71, "xera": -0.057, "era_diff": 3.77, "woba": 0.3, "xwoba": 0.0, "woba_diff": 0.3, "barrel_pct": 0.0, "hard_hit": 0.0, "exit_velo": 0.0, "whiff_pct": 0.0}, {"name": "", "pa": 570, "era": 5.3, "xera": -0.053, "era_diff": 5.35, "woba": 0.352, "xwoba": 0.0, "woba_diff": 0.352, "barrel_pct": 0.0, "hard_hit": 0.0, "exit_velo": 0.0, "whiff_pct": 0.0}, {"name": "", "pa": 130, "era": 3.07, "xera": -0.053, "era_diff": 3.12, "woba": 0.274, "xwoba": 0.0, "woba_diff": 0.274, "barrel_pct": 0.0, "hard_hit": 0.0, "exit_velo": 0.0, "whiff_pct": 0.0}, {"name": "", "pa": 137, "era": 2.84, "xera": -0.052, "era_diff": 2.89, "woba": 0.264, "xwoba": 0.0, "woba_diff": 0.264, "barrel_pct": 0.0, "hard_hit": 0.0, "exit_velo": 0.0, "whiff_pct": 0.0}, {"name": "", "pa": 164, "era": 2.78, "xera": -0.037, "era_diff": 2.82, "woba": 0.261, "xwoba": 0.0, "woba_diff": 0.261, "barrel_pct": 0.0, "hard_hit": 0.0, "exit_velo": 0.0, "whiff_pct": 0.0}, {"name": "", "pa": 201, "era": 6.08, "xera": -0.033, "era_diff": 6.11, "woba": 0.373, "xwoba": 0.0, "woba_diff": 0.373, "barrel_pct": 0.0, "hard_hit": 0.0, "exit_velo": 0.0, "whiff_pct": 0.0}, {"name": "", "pa": 444, "era": 3.43, "xera": -0.009, "era_diff": 3.44, "woba": 0.289, "xwoba": 0.0, "woba_diff": 0.289, "barrel_pct": 0.0, "hard_hit": 0.0, "exit_velo": 0.0, "whiff_pct": 0.0}, {"name": "", "pa": 165, "era": 2.89, "xera": -0.007, "era_diff": 2.9, "woba": 0.266, "xwoba": 0.0, "woba_diff": 0.266, "barrel_pct": 0.0, "hard_hit": 0.0, "exit_velo": 0.0, "whiff_pct": 0.0}, {"name": "", "pa": 204, "era": 5.73, "xera": 0.006, "era_diff": 5.72, "woba": 0.364, "xwoba": 0.0, "woba_diff": 0.364, "barrel_pct": 0.0, "hard_hit": 0.0, "exit_velo": 0.0, "whiff_pct": 0.0}, {"name": "", "pa": 541, "era": 4.96, "xera": 0.02, "era_diff": 4.94, "woba": 0.342, "xwoba": 0.0, "woba_diff": 0.342, "barrel_pct": 0.0, "hard_hit": 0.0, "exit_velo": 0.0, "whiff_pct": 0.0}, {"name": "", "pa": 434, "era": 4.61, "xera": 0.028, "era_diff": 4.58, "woba": 0.331, "xwoba": 0.0, "woba_diff": 0.331, "barrel_pct": 0.0, "hard_hit": 0.0, "exit_velo": 0.0, "whiff_pct": 0.0}, {"name": "", "pa": 187, "era": 5.13, "xera": 0.04, "era_diff": 5.09, "woba": 0.347, "xwoba": 0.0, "woba_diff": 0.347, "barrel_pct": 0.0, "hard_hit": 0.0, "exit_velo": 0.0, "whiff_pct": 0.0}, {"name": "", "pa": 456, "era": 3.16, "xera": 0.043, "era_diff": 3.12, "woba": 0.278, "xwoba": 0.0, "woba_diff": 0.278, "barrel_pct": 0.0, "hard_hit": 0.0, "exit_velo": 0.0, "whiff_pct": 0.0}, {"name": "", "pa": 174, "era": 4.02, "xera": 0.043, "era_diff": 3.98, "woba": 0.311, "xwoba": 0.0, "woba_diff": 0.311, "barrel_pct": 0.0, "hard_hit": 0.0, "exit_velo": 0.0, "whiff_pct": 0.0}, {"name": "", "pa": 176, "era": 2.82, "xera": 0.044, "era_diff": 2.78, "woba": 0.263, "xwoba": 0.0, "woba_diff": 0.263, "barrel_pct": 0.0, "hard_hit": 0.0, "exit_velo": 0.0, "whiff_pct": 0.0}, {"name": "", "pa": 212, "era": 3.79, "xera": 0.049, "era_diff": 3.74, "woba": 0.303, "xwoba": 0.0, "woba_diff": 0.303, "barrel_pct": 0.0, "hard_hit": 0.0, "exit_velo": 0.0, "whiff_pct": 0.0}, {"name": "", "pa": 111, "era": 2.0, "xera": 0.051, "era_diff": 1.95, "woba": 0.221, "xwoba": 0.0, "woba_diff": 0.221, "barrel_pct": 0.0, "hard_hit": 0.0, "exit_velo": 0.0, "whiff_pct": 0.0}, {"name": "", "pa": 175, "era": 3.14, "xera": 0.068, "era_diff": 3.07, "woba": 0.277, "xwoba": 0.0, "woba_diff": 0.277, "barrel_pct": 0.0, "hard_hit": 0.0, "exit_velo": 0.0, "whiff_pct": 0.0}, {"name": "", "pa": 176, "era": 3.88, "xera": 0.071, "era_diff": 3.81, "woba": 0.306, "xwoba": 0.0, "woba_diff": 0.306, "barrel_pct": 0.0, "hard_hit": 0.0, "exit_velo": 0.0, "whiff_pct": 0.0}, {"name": "", "pa": 470, "era": 5.41, "xera": 0.079, "era_diff": 5.33, "woba": 0.355, "xwoba": 0.0, "woba_diff": 0.355, "barrel_pct": 0.0, "hard_hit": 0.0, "exit_velo": 0.0, "whiff_pct": 0.0}, {"name": "", "pa": 188, "era": 4.27, "xera": 0.089, "era_diff": 4.18, "woba": 0.32, "xwoba": 0.0, "woba_diff": 0.32, "barrel_pct": 0.0, "hard_hit": 0.0, "exit_velo": 0.0, "whiff_pct": 0.0}, {"name": "", "pa": 158, "era": 4.16, "xera": 0.093, "era_diff": 4.07, "woba": 0.316, "xwoba": 0.0, "woba_diff": 0.316, "barrel_pct": 0.0, "hard_hit": 0.0, "exit_velo": 0.0, "whiff_pct": 0.0}, {"name": "", "pa": 153, "era": 3.26, "xera": 0.094, "era_diff": 3.17, "woba": 0.282, "xwoba": 0.0, "woba_diff": 0.282, "barrel_pct": 0.0, "hard_hit": 0.0, "exit_velo": 0.0, "whiff_pct": 0.0}, {"name": "", "pa": 188, "era": 4.7, "xera": 0.097, "era_diff": 4.6, "woba": 0.334, "xwoba": 0.0, "woba_diff": 0.334, "barrel_pct": 0.0, "hard_hit": 0.0, "exit_velo": 0.0, "whiff_pct": 0.0}, {"name": "", "pa": 101, "era": 2.53, "xera": 0.097, "era_diff": 2.43, "woba": 0.249, "xwoba": 0.0, "woba_diff": 0.249, "barrel_pct": 0.0, "hard_hit": 0.0, "exit_velo": 0.0, "whiff_pct": 0.0}, {"name": "", "pa": 191, "era": 3.48, "xera": 0.102, "era_diff": 3.38, "woba": 0.291, "xwoba": 0.0, "woba_diff": 0.291, "barrel_pct": 0.0, "hard_hit": 0.0, "exit_velo": 0.0, "whiff_pct": 0.0}, {"name": "", "pa": 595, "era": 5.59, "xera": 0.11, "era_diff": 5.48, "woba": 0.36, "xwoba": 0.0, "woba_diff": 0.36, "barrel_pct": 0.0, "hard_hit": 0.0, "exit_velo": 0.0, "whiff_pct": 0.0}, {"name": "", "pa": 145, "era": 2.49, "xera": 0.123, "era_diff": 2.37, "woba": 0.247, "xwoba": 0.0, "woba_diff": 0.247, "barrel_pct": 0.0, "hard_hit": 0.0, "exit_velo": 0.0, "whiff_pct": 0.0}, {"name": "", "pa": 186, "era": 2.89, "xera": 0.125, "era_diff": 2.77, "woba": 0.266, "xwoba": 0.0, "woba_diff": 0.266, "barrel_pct": 0.0, "hard_hit": 0.0, "exit_velo": 0.0, "whiff_pct": 0.0}, {"name": "", "pa": 151, "era": 2.49, "xera": 0.148, "era_diff": 2.34, "woba": 0.247, "xwoba": 0.0, "woba_diff": 0.247, "barrel_pct": 0.0, "hard_hit": 0.0, "exit_velo": 0.0, "whiff_pct": 0.0}, {"name": "", "pa": 193, "era": 4.02, "xera": 0.155, "era_diff": 3.86, "woba": 0.311, "xwoba": 0.0, "woba_diff": 0.311, "barrel_pct": 0.0, "hard_hit": 0.0, "exit_velo": 0.0, "whiff_pct": 0.0}, {"name": "", "pa": 173, "era": 4.45, "xera": 0.156, "era_diff": 4.29, "woba": 0.326, "xwoba": 0.0, "woba_diff": 0.326, "barrel_pct": 0.0, "hard_hit": 0.0, "exit_velo": 0.0, "whiff_pct": 0.0}, {"name": "", "pa": 192, "era": 3.96, "xera": 0.171, "era_diff": 3.79, "woba": 0.309, "xwoba": 0.0, "woba_diff": 0.309, "barrel_pct": 0.0, "hard_hit": 0.0, "exit_velo": 0.0, "whiff_pct": 0.0}, {"name": "", "pa": 192, "era": 4.16, "xera": 0.204, "era_diff": 3.96, "woba": 0.316, "xwoba": 0.0, "woba_diff": 0.316, "barrel_pct": 0.0, "hard_hit": 0.0, "exit_velo": 0.0, "whiff_pct": 0.0}, {"name": "", "pa": 449, "era": 3.66, "xera": 0.206, "era_diff": 3.45, "woba": 0.298, "xwoba": 0.0, "woba_diff": 0.298, "barrel_pct": 0.0, "hard_hit": 0.0, "exit_velo": 0.0, "whiff_pct": 0.0}, {"name": "", "pa": 349, "era": 2.49, "xera": 0.216, "era_diff": 2.27, "woba": 0.247, "xwoba": 0.0, "woba_diff": 0.247, "barrel_pct": 0.0, "hard_hit": 0.0, "exit_velo": 0.0, "whiff_pct": 0.0}, {"name": "", "pa": 488, "era": 4.04, "xera": 0.22, "era_diff": 3.82, "woba": 0.312, "xwoba": 0.0, "woba_diff": 0.312, "barrel_pct": 0.0, "hard_hit": 0.0, "exit_velo": 0.0, "whiff_pct": 0.0}, {"name": "", "pa": 315, "era": 3.82, "xera": 0.222, "era_diff": 3.6, "woba": 0.304, "xwoba": 0.0, "woba_diff": 0.304, "barrel_pct": 0.0, "hard_hit": 0.0, "exit_velo": 0.0, "whiff_pct": 0.0}, {"name": "", "pa": 388, "era": 5.81, "xera": 0.232, "era_diff": 5.58, "woba": 0.366, "xwoba": 0.0, "woba_diff": 0.366, "barrel_pct": 0.0, "hard_hit": 0.0, "exit_velo": 0.0, "whiff_pct": 0.0}, {"name": "", "pa": 209, "era": 2.69, "xera": 0.258, "era_diff": 2.43, "woba": 0.257, "xwoba": 0.0, "woba_diff": 0.257, "barrel_pct": 0.0, "hard_hit": 0.0, "exit_velo": 0.0, "whiff_pct": 0.0}, {"name": "", "pa": 180, "era": 3.85, "xera": 0.259, "era_diff": 3.59, "woba": 0.305, "xwoba": 0.0, "woba_diff": 0.305, "barrel_pct": 0.0, "hard_hit": 0.0, "exit_velo": 0.0, "whiff_pct": 0.0}, {"name": "", "pa": 247, "era": 3.69, "xera": 0.284, "era_diff": 3.41, "woba": 0.299, "xwoba": 0.0, "woba_diff": 0.299, "barrel_pct": 0.0, "hard_hit": 0.0, "exit_velo": 0.0, "whiff_pct": 0.0}, {"name": "", "pa": 202, "era": 4.1, "xera": 0.292, "era_diff": 3.81, "woba": 0.314, "xwoba": 0.0, "woba_diff": 0.314, "barrel_pct": 0.0, "hard_hit": 0.0, "exit_velo": 0.0, "whiff_pct": 0.0}, {"name": "", "pa": 212, "era": 3.02, "xera": 0.298, "era_diff": 2.72, "woba": 0.272, "xwoba": 0.0, "woba_diff": 0.272, "barrel_pct": 0.0, "hard_hit": 0.0, "exit_velo": 0.0, "whiff_pct": 0.0}, {"name": "", "pa": 154, "era": 3.16, "xera": 0.314, "era_diff": 2.85, "woba": 0.278, "xwoba": 0.0, "woba_diff": 0.278, "barrel_pct": 0.0, "hard_hit": 0.0, "exit_velo": 0.0, "whiff_pct": 0.0}, {"name": "", "pa": 518, "era": 5.03, "xera": 0.324, "era_diff": 4.71, "woba": 0.344, "xwoba": 0.0, "woba_diff": 0.344, "barrel_pct": 0.0, "hard_hit": 0.0, "exit_velo": 0.0, "whiff_pct": 0.0}, {"name": "", "pa": 174, "era": 3.85, "xera": 0.327, "era_diff": 3.52, "woba": 0.305, "xwoba": 0.0, "woba_diff": 0.305, "barrel_pct": 0.0, "hard_hit": 0.0, "exit_velo": 0.0, "whiff_pct": 0.0}, {"name": "", "pa": 351, "era": 3.88, "xera": 0.334, "era_diff": 3.55, "woba": 0.306, "xwoba": 0.0, "woba_diff": 0.306, "barrel_pct": 0.0, "hard_hit": 0.0, "exit_velo": 0.0, "whiff_pct": 0.0}, {"name": "", "pa": 308, "era": 4.64, "xera": 0.336, "era_diff": 4.3, "woba": 0.332, "xwoba": 0.0, "woba_diff": 0.332, "barrel_pct": 0.0, "hard_hit": 0.0, "exit_velo": 0.0, "whiff_pct": 0.0}, {"name": "", "pa": 324, "era": 3.09, "xera": 0.345, "era_diff": 2.75, "woba": 0.275, "xwoba": 0.0, "woba_diff": 0.275, "barrel_pct": 0.0, "hard_hit": 0.0, "exit_velo": 0.0, "whiff_pct": 0.0}, {"name": "", "pa": 159, "era": 3.61, "xera": 0.348, "era_diff": 3.26, "woba": 0.296, "xwoba": 0.0, "woba_diff": 0.296, "barrel_pct": 0.0, "hard_hit": 0.0, "exit_velo": 0.0, "whiff_pct": 0.0}, {"name": "", "pa": 176, "era": 2.93, "xera": 0.363, "era_diff": 2.57, "woba": 0.268, "xwoba": 0.0, "woba_diff": 0.268, "barrel_pct": 0.0, "hard_hit": 0.0, "exit_velo": 0.0, "whiff_pct": 0.0}, {"name": "", "pa": 518, "era": 3.82, "xera": 0.374, "era_diff": 3.45, "woba": 0.304, "xwoba": 0.0, "woba_diff": 0.304, "barrel_pct": 0.0, "hard_hit": 0.0, "exit_velo": 0.0, "whiff_pct": 0.0}, {"name": "", "pa": 147, "era": 3.51, "xera": 0.394, "era_diff": 3.12, "woba": 0.292, "xwoba": 0.0, "woba_diff": 0.292, "barrel_pct": 0.0, "hard_hit": 0.0, "exit_velo": 0.0, "whiff_pct": 0.0}, {"name": "", "pa": 508, "era": 3.88, "xera": 0.404, "era_diff": 3.48, "woba": 0.306, "xwoba": 0.0, "woba_diff": 0.306, "barrel_pct": 0.0, "hard_hit": 0.0, "exit_velo": 0.0, "whiff_pct": 0.0}, {"name": "", "pa": 171, "era": 2.61, "xera": 0.404, "era_diff": 2.21, "woba": 0.253, "xwoba": 0.0, "woba_diff": 0.253, "barrel_pct": 0.0, "hard_hit": 0.0, "exit_velo": 0.0, "whiff_pct": 0.0}, {"name": "", "pa": 280, "era": 5.27, "xera": 0.409, "era_diff": 4.86, "woba": 0.351, "xwoba": 0.0, "woba_diff": 0.351, "barrel_pct": 0.0, "hard_hit": 0.0, "exit_velo": 0.0, "whiff_pct": 0.0}, {"name": "", "pa": 519, "era": 4.04, "xera": 0.415, "era_diff": 3.62, "woba": 0.312, "xwoba": 0.0, "woba_diff": 0.312, "barrel_pct": 0.0, "hard_hit": 0.0, "exit_velo": 0.0, "whiff_pct": 0.0}, {"name": "", "pa": 173, "era": 2.51, "xera": 0.422, "era_diff": 2.09, "woba": 0.248, "xwoba": 0.0, "woba_diff": 0.248, "barrel_pct": 0.0, "hard_hit": 0.0, "exit_velo": 0.0, "whiff_pct": 0.0}, {"name": "", "pa": 218, "era": 4.1, "xera": 0.422, "era_diff": 3.68, "woba": 0.314, "xwoba": 0.0, "woba_diff": 0.314, "barrel_pct": 0.0, "hard_hit": 0.0, "exit_velo": 0.0, "whiff_pct": 0.0}, {"name": "", "pa": 199, "era": 3.53, "xera": 0.433, "era_diff": 3.1, "woba": 0.293, "xwoba": 0.0, "woba_diff": 0.293, "barrel_pct": 0.0, "hard_hit": 0.0, "exit_velo": 0.0, "whiff_pct": 0.0}, {"name": "", "pa": 145, "era": 4.3, "xera": 0.437, "era_diff": 3.86, "woba": 0.321, "xwoba": 0.0, "woba_diff": 0.321, "barrel_pct": 0.0, "hard_hit": 0.0, "exit_velo": 0.0, "whiff_pct": 0.0}, {"name": "", "pa": 241, "era": 3.64, "xera": 0.439, "era_diff": 3.2, "woba": 0.297, "xwoba": 0.0, "woba_diff": 0.297, "barrel_pct": 0.0, "hard_hit": 0.0, "exit_velo": 0.0, "whiff_pct": 0.0}, {"name": "", "pa": 335, "era": 5.37, "xera": 0.447, "era_diff": 4.92, "woba": 0.354, "xwoba": 0.0, "woba_diff": 0.354, "barrel_pct": 0.0, "hard_hit": 0.0, "exit_velo": 0.0, "whiff_pct": 0.0}, {"name": "", "pa": 255, "era": 5.88, "xera": 0.452, "era_diff": 5.43, "woba": 0.368, "xwoba": 0.0, "woba_diff": 0.368, "barrel_pct": 0.0, "hard_hit": 0.0, "exit_velo": 0.0, "whiff_pct": 0.0}, {"name": "", "pa": 254, "era": 5.37, "xera": 0.504, "era_diff": 4.87, "woba": 0.354, "xwoba": 0.0, "woba_diff": 0.354, "barrel_pct": 0.0, "hard_hit": 0.0, "exit_velo": 0.0, "whiff_pct": 0.0}, {"name": "", "pa": 489, "era": 4.51, "xera": 0.505, "era_diff": 4.0, "woba": 0.328, "xwoba": 0.0, "woba_diff": 0.328, "barrel_pct": 0.0, "hard_hit": 0.0, "exit_velo": 0.0, "whiff_pct": 0.0}, {"name": "", "pa": 163, "era": 3.99, "xera": 0.51, "era_diff": 3.48, "woba": 0.31, "xwoba": 0.0, "woba_diff": 0.31, "barrel_pct": 0.0, "hard_hit": 0.0, "exit_velo": 0.0, "whiff_pct": 0.0}, {"name": "", "pa": 195, "era": 3.46, "xera": 0.535, "era_diff": 2.92, "woba": 0.29, "xwoba": 0.0, "woba_diff": 0.29, "barrel_pct": 0.0, "hard_hit": 0.0, "exit_velo": 0.0, "whiff_pct": 0.0}, {"name": "", "pa": 153, "era": 4.86, "xera": 0.54, "era_diff": 4.32, "woba": 0.339, "xwoba": 0.0, "woba_diff": 0.339, "barrel_pct": 0.0, "hard_hit": 0.0, "exit_velo": 0.0, "whiff_pct": 0.0}, {"name": "", "pa": 156, "era": 4.19, "xera": 0.547, "era_diff": 3.64, "woba": 0.317, "xwoba": 0.0, "woba_diff": 0.317, "barrel_pct": 0.0, "hard_hit": 0.0, "exit_velo": 0.0, "whiff_pct": 0.0}, {"name": "", "pa": 251, "era": 4.64, "xera": 0.548, "era_diff": 4.09, "woba": 0.332, "xwoba": 0.0, "woba_diff": 0.332, "barrel_pct": 0.0, "hard_hit": 0.0, "exit_velo": 0.0, "whiff_pct": 0.0}, {"name": "", "pa": 568, "era": 4.27, "xera": 0.558, "era_diff": 3.71, "woba": 0.32, "xwoba": 0.0, "woba_diff": 0.32, "barrel_pct": 0.0, "hard_hit": 0.0, "exit_velo": 0.0, "whiff_pct": 0.0}, {"name": "", "pa": 491, "era": 4.73, "xera": 0.566, "era_diff": 4.16, "woba": 0.335, "xwoba": 0.0, "woba_diff": 0.335, "barrel_pct": 0.0, "hard_hit": 0.0, "exit_velo": 0.0, "whiff_pct": 0.0}, {"name": "", "pa": 482, "era": 3.33, "xera": 0.59, "era_diff": 2.74, "woba": 0.285, "xwoba": 0.0, "woba_diff": 0.285, "barrel_pct": 0.0, "hard_hit": 0.0, "exit_velo": 0.0, "whiff_pct": 0.0}, {"name": "", "pa": 536, "era": 3.64, "xera": 0.605, "era_diff": 3.04, "woba": 0.297, "xwoba": 0.0, "woba_diff": 0.297, "barrel_pct": 0.0, "hard_hit": 0.0, "exit_velo": 0.0, "whiff_pct": 0.0}, {"name": "", "pa": 133, "era": 2.78, "xera": 0.616, "era_diff": 2.16, "woba": 0.261, "xwoba": 0.0, "woba_diff": 0.261, "barrel_pct": 0.0, "hard_hit": 0.0, "exit_velo": 0.0, "whiff_pct": 0.0}, {"name": "", "pa": 212, "era": 3.88, "xera": 0.62, "era_diff": 3.26, "woba": 0.306, "xwoba": 0.0, "woba_diff": 0.306, "barrel_pct": 0.0, "hard_hit": 0.0, "exit_velo": 0.0, "whiff_pct": 0.0}, {"name": "", "pa": 172, "era": 3.74, "xera": 0.628, "era_diff": 3.11, "woba": 0.301, "xwoba": 0.0, "woba_diff": 0.301, "barrel_pct": 0.0, "hard_hit": 0.0, "exit_velo": 0.0, "whiff_pct": 0.0}, {"name": "", "pa": 137, "era": 4.04, "xera": 0.633, "era_diff": 3.41, "woba": 0.312, "xwoba": 0.0, "woba_diff": 0.312, "barrel_pct": 0.0, "hard_hit": 0.0, "exit_velo": 0.0, "whiff_pct": 0.0}, {"name": "", "pa": 429, "era": 3.99, "xera": 0.65, "era_diff": 3.34, "woba": 0.31, "xwoba": 0.0, "woba_diff": 0.31, "barrel_pct": 0.0, "hard_hit": 0.0, "exit_velo": 0.0, "whiff_pct": 0.0}, {"name": "", "pa": 150, "era": 3.46, "xera": 0.656, "era_diff": 2.8, "woba": 0.29, "xwoba": 0.0, "woba_diff": 0.29, "barrel_pct": 0.0, "hard_hit": 0.0, "exit_velo": 0.0, "whiff_pct": 0.0}, {"name": "", "pa": 168, "era": 2.96, "xera": 0.659, "era_diff": 2.3, "woba": 0.269, "xwoba": 0.0, "woba_diff": 0.269, "barrel_pct": 0.0, "hard_hit": 0.0, "exit_velo": 0.0, "whiff_pct": 0.0}, {"name": "", "pa": 140, "era": 5.55, "xera": 0.681, "era_diff": 4.87, "woba": 0.359, "xwoba": 0.0, "woba_diff": 0.359, "barrel_pct": 0.0, "hard_hit": 0.0, "exit_velo": 0.0, "whiff_pct": 0.0}, {"name": "", "pa": 166, "era": 2.76, "xera": 0.692, "era_diff": 2.07, "woba": 0.26, "xwoba": 0.0, "woba_diff": 0.26, "barrel_pct": 0.0, "hard_hit": 0.0, "exit_velo": 0.0, "whiff_pct": 0.0}, {"name": "", "pa": 286, "era": 4.64, "xera": 0.697, "era_diff": 3.94, "woba": 0.332, "xwoba": 0.0, "woba_diff": 0.332, "barrel_pct": 0.0, "hard_hit": 0.0, "exit_velo": 0.0, "whiff_pct": 0.0}, {"name": "", "pa": 536, "era": 4.64, "xera": 0.719, "era_diff": 3.92, "woba": 0.332, "xwoba": 0.0, "woba_diff": 0.332, "barrel_pct": 0.0, "hard_hit": 0.0, "exit_velo": 0.0, "whiff_pct": 0.0}, {"name": "", "pa": 157, "era": 3.19, "xera": 0.727, "era_diff": 2.46, "woba": 0.279, "xwoba": 0.0, "woba_diff": 0.279, "barrel_pct": 0.0, "hard_hit": 0.0, "exit_velo": 0.0, "whiff_pct": 0.0}, {"name": "", "pa": 468, "era": 4.36, "xera": 0.745, "era_diff": 3.62, "woba": 0.323, "xwoba": 0.0, "woba_diff": 0.323, "barrel_pct": 0.0, "hard_hit": 0.0, "exit_velo": 0.0, "whiff_pct": 0.0}, {"name": "", "pa": 307, "era": 4.1, "xera": 0.753, "era_diff": 3.35, "woba": 0.314, "xwoba": 0.0, "woba_diff": 0.314, "barrel_pct": 0.0, "hard_hit": 0.0, "exit_velo": 0.0, "whiff_pct": 0.0}, {"name": "", "pa": 424, "era": 4.24, "xera": 0.802, "era_diff": 3.44, "woba": 0.319, "xwoba": 0.0, "woba_diff": 0.319, "barrel_pct": 0.0, "hard_hit": 0.0, "exit_velo": 0.0, "whiff_pct": 0.0}, {"name": "", "pa": 165, "era": 4.48, "xera": 0.824, "era_diff": 3.66, "woba": 0.327, "xwoba": 0.0, "woba_diff": 0.327, "barrel_pct": 0.0, "hard_hit": 0.0, "exit_velo": 0.0, "whiff_pct": 0.0}, {"name": "", "pa": 533, "era": 3.93, "xera": 0.825, "era_diff": 3.11, "woba": 0.308, "xwoba": 0.0, "woba_diff": 0.308, "barrel_pct": 0.0, "hard_hit": 0.0, "exit_velo": 0.0, "whiff_pct": 0.0}, {"name": "", "pa": 452, "era": 5.81, "xera": 0.887, "era_diff": 4.92, "woba": 0.366, "xwoba": 0.0, "woba_diff": 0.366, "barrel_pct": 0.0, "hard_hit": 0.0, "exit_velo": 0.0, "whiff_pct": 0.0}, {"name": "", "pa": 242, "era": 4.67, "xera": 0.889, "era_diff": 3.78, "woba": 0.333, "xwoba": 0.0, "woba_diff": 0.333, "barrel_pct": 0.0, "hard_hit": 0.0, "exit_velo": 0.0, "whiff_pct": 0.0}, {"name": "", "pa": 184, "era": 3.43, "xera": 0.89, "era_diff": 2.54, "woba": 0.289, "xwoba": 0.0, "woba_diff": 0.289, "barrel_pct": 0.0, "hard_hit": 0.0, "exit_velo": 0.0, "whiff_pct": 0.0}, {"name": "", "pa": 158, "era": 3.58, "xera": 0.895, "era_diff": 2.69, "woba": 0.295, "xwoba": 0.0, "woba_diff": 0.295, "barrel_pct": 0.0, "hard_hit": 0.0, "exit_velo": 0.0, "whiff_pct": 0.0}, {"name": "", "pa": 154, "era": 3.74, "xera": 0.915, "era_diff": 2.83, "woba": 0.301, "xwoba": 0.0, "woba_diff": 0.301, "barrel_pct": 0.0, "hard_hit": 0.0, "exit_velo": 0.0, "whiff_pct": 0.0}, {"name": "", "pa": 230, "era": 3.56, "xera": 0.92, "era_diff": 2.64, "woba": 0.294, "xwoba": 0.0, "woba_diff": 0.294, "barrel_pct": 0.0, "hard_hit": 0.0, "exit_velo": 0.0, "whiff_pct": 0.0}, {"name": "", "pa": 238, "era": 3.71, "xera": 0.925, "era_diff": 2.79, "woba": 0.3, "xwoba": 0.0, "woba_diff": 0.3, "barrel_pct": 0.0, "hard_hit": 0.0, "exit_velo": 0.0, "whiff_pct": 0.0}, {"name": "", "pa": 375, "era": 5.88, "xera": 0.931, "era_diff": 4.95, "woba": 0.368, "xwoba": 0.0, "woba_diff": 0.368, "barrel_pct": 0.0, "hard_hit": 0.0, "exit_velo": 0.0, "whiff_pct": 0.0}, {"name": "", "pa": 418, "era": 4.1, "xera": 0.947, "era_diff": 3.15, "woba": 0.314, "xwoba": 0.0, "woba_diff": 0.314, "barrel_pct": 0.0, "hard_hit": 0.0, "exit_velo": 0.0, "whiff_pct": 0.0}, {"name": "", "pa": 152, "era": 3.41, "xera": 0.954, "era_diff": 2.46, "woba": 0.288, "xwoba": 0.0, "woba_diff": 0.288, "barrel_pct": 0.0, "hard_hit": 0.0, "exit_velo": 0.0, "whiff_pct": 0.0}, {"name": "", "pa": 161, "era": 3.26, "xera": 0.967, "era_diff": 2.29, "woba": 0.282, "xwoba": 0.0, "woba_diff": 0.282, "barrel_pct": 0.0, "hard_hit": 0.0, "exit_velo": 0.0, "whiff_pct": 0.0}, {"name": "", "pa": 156, "era": 2.22, "xera": 0.981, "era_diff": 1.24, "woba": 0.233, "xwoba": 0.0, "woba_diff": 0.233, "barrel_pct": 0.0, "hard_hit": 0.0, "exit_velo": 0.0, "whiff_pct": 0.0}, {"name": "", "pa": 162, "era": 2.98, "xera": 0.982, "era_diff": 2.0, "woba": 0.27, "xwoba": 0.0, "woba_diff": 0.27, "barrel_pct": 0.0, "hard_hit": 0.0, "exit_velo": 0.0, "whiff_pct": 0.0}, {"name": "", "pa": 240, "era": 3.53, "xera": 0.987, "era_diff": 2.54, "woba": 0.293, "xwoba": 0.0, "woba_diff": 0.293, "barrel_pct": 0.0, "hard_hit": 0.0, "exit_velo": 0.0, "whiff_pct": 0.0}, {"name": "", "pa": 462, "era": 3.88, "xera": 0.99, "era_diff": 2.89, "woba": 0.306, "xwoba": 0.0, "woba_diff": 0.306, "barrel_pct": 0.0, "hard_hit": 0.0, "exit_velo": 0.0, "whiff_pct": 0.0}, {"name": "", "pa": 536, "era": 4.3, "xera": 1.011, "era_diff": 3.29, "woba": 0.321, "xwoba": 0.0, "woba_diff": 0.321, "barrel_pct": 0.0, "hard_hit": 0.0, "exit_velo": 0.0, "whiff_pct": 0.0}, {"name": "", "pa": 245, "era": 3.23, "xera": 1.018, "era_diff": 2.21, "woba": 0.281, "xwoba": 0.0, "woba_diff": 0.281, "barrel_pct": 0.0, "hard_hit": 0.0, "exit_velo": 0.0, "whiff_pct": 0.0}, {"name": "", "pa": 234, "era": 4.73, "xera": 1.038, "era_diff": 3.69, "woba": 0.335, "xwoba": 0.0, "woba_diff": 0.335, "barrel_pct": 0.0, "hard_hit": 0.0, "exit_velo": 0.0, "whiff_pct": 0.0}, {"name": "", "pa": 306, "era": 4.55, "xera": 1.052, "era_diff": 3.5, "woba": 0.329, "xwoba": 0.0, "woba_diff": 0.329, "barrel_pct": 0.0, "hard_hit": 0.0, "exit_velo": 0.0, "whiff_pct": 0.0}, {"name": "", "pa": 315, "era": 4.61, "xera": 1.056, "era_diff": 3.55, "woba": 0.331, "xwoba": 0.0, "woba_diff": 0.331, "barrel_pct": 0.0, "hard_hit": 0.0, "exit_velo": 0.0, "whiff_pct": 0.0}, {"name": "", "pa": 429, "era": 3.46, "xera": 1.094, "era_diff": 2.37, "woba": 0.29, "xwoba": 0.0, "woba_diff": 0.29, "barrel_pct": 0.0, "hard_hit": 0.0, "exit_velo": 0.0, "whiff_pct": 0.0}, {"name": "", "pa": 118, "era": 4.58, "xera": 1.094, "era_diff": 3.49, "woba": 0.33, "xwoba": 0.0, "woba_diff": 0.33, "barrel_pct": 0.0, "hard_hit": 0.0, "exit_velo": 0.0, "whiff_pct": 0.0}, {"name": "", "pa": 144, "era": 3.74, "xera": 1.101, "era_diff": 2.64, "woba": 0.301, "xwoba": 0.0, "woba_diff": 0.301, "barrel_pct": 0.0, "hard_hit": 0.0, "exit_velo": 0.0, "whiff_pct": 0.0}, {"name": "", "pa": 133, "era": 3.31, "xera": 1.133, "era_diff": 2.18, "woba": 0.284, "xwoba": 0.0, "woba_diff": 0.284, "barrel_pct": 0.0, "hard_hit": 0.0, "exit_velo": 0.0, "whiff_pct": 0.0}, {"name": "", "pa": 417, "era": 4.67, "xera": 1.161, "era_diff": 3.51, "woba": 0.333, "xwoba": 0.0, "woba_diff": 0.333, "barrel_pct": 0.0, "hard_hit": 0.0, "exit_velo": 0.0, "whiff_pct": 0.0}, {"name": "", "pa": 166, "era": 5.34, "xera": 1.166, "era_diff": 4.17, "woba": 0.353, "xwoba": 0.0, "woba_diff": 0.353, "barrel_pct": 0.0, "hard_hit": 0.0, "exit_velo": 0.0, "whiff_pct": 0.0}, {"name": "", "pa": 256, "era": 3.74, "xera": 1.341, "era_diff": 2.4, "woba": 0.301, "xwoba": 0.0, "woba_diff": 0.301, "barrel_pct": 0.0, "hard_hit": 0.0, "exit_velo": 0.0, "whiff_pct": 0.0}, {"name": "", "pa": 315, "era": 4.55, "xera": 1.375, "era_diff": 3.17, "woba": 0.329, "xwoba": 0.0, "woba_diff": 0.329, "barrel_pct": 0.0, "hard_hit": 0.0, "exit_velo": 0.0, "whiff_pct": 0.0}, {"name": "", "pa": 304, "era": 5.13, "xera": 1.39, "era_diff": 3.74, "woba": 0.347, "xwoba": 0.0, "woba_diff": 0.347, "barrel_pct": 0.0, "hard_hit": 0.0, "exit_velo": 0.0, "whiff_pct": 0.0}, {"name": "", "pa": 170, "era": 3.69, "xera": 1.431, "era_diff": 2.26, "woba": 0.299, "xwoba": 0.0, "woba_diff": 0.299, "barrel_pct": 0.0, "hard_hit": 0.0, "exit_velo": 0.0, "whiff_pct": 0.0}, {"name": "", "pa": 244, "era": 4.48, "xera": 1.45, "era_diff": 3.03, "woba": 0.327, "xwoba": 0.0, "woba_diff": 0.327, "barrel_pct": 0.0, "hard_hit": 0.0, "exit_velo": 0.0, "whiff_pct": 0.0}, {"name": "", "pa": 220, "era": 6.04, "xera": 1.451, "era_diff": 4.59, "woba": 0.372, "xwoba": 0.0, "woba_diff": 0.372, "barrel_pct": 0.0, "hard_hit": 0.0, "exit_velo": 0.0, "whiff_pct": 0.0}, {"name": "", "pa": 203, "era": 5.48, "xera": 1.577, "era_diff": 3.9, "woba": 0.357, "xwoba": 0.0, "woba_diff": 0.357, "barrel_pct": 0.0, "hard_hit": 0.0, "exit_velo": 0.0, "whiff_pct": 0.0}, {"name": "", "pa": 169, "era": 4.02, "xera": 1.617, "era_diff": 2.4, "woba": 0.311, "xwoba": 0.0, "woba_diff": 0.311, "barrel_pct": 0.0, "hard_hit": 0.0, "exit_velo": 0.0, "whiff_pct": 0.0}, {"name": "", "pa": 285, "era": 4.58, "xera": 1.626, "era_diff": 2.95, "woba": 0.33, "xwoba": 0.0, "woba_diff": 0.33, "barrel_pct": 0.0, "hard_hit": 0.0, "exit_velo": 0.0, "whiff_pct": 0.0}, {"name": "", "pa": 154, "era": 3.85, "xera": 1.68, "era_diff": 2.17, "woba": 0.305, "xwoba": 0.0, "woba_diff": 0.305, "barrel_pct": 0.0, "hard_hit": 0.0, "exit_velo": 0.0, "whiff_pct": 0.0}, {"name": "", "pa": 161, "era": 5.37, "xera": 1.725, "era_diff": 3.65, "woba": 0.354, "xwoba": 0.0, "woba_diff": 0.354, "barrel_pct": 0.0, "hard_hit": 0.0, "exit_velo": 0.0, "whiff_pct": 0.0}, {"name": "", "pa": 203, "era": 3.64, "xera": 1.735, "era_diff": 1.91, "woba": 0.297, "xwoba": 0.0, "woba_diff": 0.297, "barrel_pct": 0.0, "hard_hit": 0.0, "exit_velo": 0.0, "whiff_pct": 0.0}, {"name": "", "pa": 222, "era": 7.62, "xera": 1.738, "era_diff": 5.88, "woba": 0.409, "xwoba": 0.0, "woba_diff": 0.409, "barrel_pct": 0.0, "hard_hit": 0.0, "exit_velo": 0.0, "whiff_pct": 0.0}, {"name": "", "pa": 165, "era": 4.48, "xera": 1.738, "era_diff": 2.74, "woba": 0.327, "xwoba": 0.0, "woba_diff": 0.327, "barrel_pct": 0.0, "hard_hit": 0.0, "exit_velo": 0.0, "whiff_pct": 0.0}, {"name": "", "pa": 140, "era": 3.02, "xera": 1.77, "era_diff": 1.25, "woba": 0.272, "xwoba": 0.0, "woba_diff": 0.272, "barrel_pct": 0.0, "hard_hit": 0.0, "exit_velo": 0.0, "whiff_pct": 0.0}, {"name": "", "pa": 137, "era": 3.82, "xera": 1.797, "era_diff": 2.02, "woba": 0.304, "xwoba": 0.0, "woba_diff": 0.304, "barrel_pct": 0.0, "hard_hit": 0.0, "exit_velo": 0.0, "whiff_pct": 0.0}, {"name": "", "pa": 149, "era": 6.19, "xera": 1.848, "era_diff": 4.34, "woba": 0.376, "xwoba": 0.0, "woba_diff": 0.376, "barrel_pct": 0.0, "hard_hit": 0.0, "exit_velo": 0.0, "whiff_pct": 0.0}, {"name": "", "pa": 275, "era": 4.13, "xera": 1.881, "era_diff": 2.25, "woba": 0.315, "xwoba": 0.0, "woba_diff": 0.315, "barrel_pct": 0.0, "hard_hit": 0.0, "exit_velo": 0.0, "whiff_pct": 0.0}, {"name": "", "pa": 187, "era": 4.27, "xera": 1.973, "era_diff": 2.3, "woba": 0.32, "xwoba": 0.0, "woba_diff": 0.32, "barrel_pct": 0.0, "hard_hit": 0.0, "exit_velo": 0.0, "whiff_pct": 0.0}, {"name": "", "pa": 137, "era": 2.67, "xera": 2.0, "era_diff": 0.67, "woba": 0.256, "xwoba": 0.0, "woba_diff": 0.256, "barrel_pct": 0.0, "hard_hit": 0.0, "exit_velo": 0.0, "whiff_pct": 0.0}, {"name": "", "pa": 215, "era": 4.61, "xera": 2.34, "era_diff": 2.27, "woba": 0.331, "xwoba": 0.0, "woba_diff": 0.331, "barrel_pct": 0.0, "hard_hit": 0.0, "exit_velo": 0.0, "whiff_pct": 0.0}]